Workbook

Sheet Mii List
A1: Name | B1: Gender | C1: ❤︎♂? | D1: ❤︎♀? | E1: ❤︎⚧? | G1: 📊 SUMMARY
A2: Robin | B2: Nonbinary | C2: ✓ | D2: ✓ | E2: ✓ | G2: Total Miis | H2: =COUNTA(A2:A200) -> 50
A3: Nny | B3: Nonbinary | C3: ✗ | D3: ✗ | E3: ✗ | G3: Male | H3: =COUNTIF(B:B,"Male") -> 32 | I3: Likes ♂ | J3: =COUNTIF(C2:C50,"✓") -> 32
A4: Barack Obama | B4: Male | C4: ✗ | D4: ✓ | E4: ✗ | G4: Female | H4: =COUNTIF(B:B,"Female") -> 16 | I4: Likes ♀ | J4: =COUNTIF(D2:D50,"✓") -> 39
A5: Randy Sexton | B5: Male | C5: ✓ | D5: ✓ | E5: ✓ | G5: Nonbinary | H5: =COUNTIF(B:B,"Nonbinary") -> 2 | I5: Likes ⚧ | J5: =COUNTIF(E2:E50,"✓") -> 23
A6: Biff Williams | B6: Male | C6: ✗ | D6: ✓ | E6: ✗
A7: Michael Newman | B7: Male | C7: ✓ | D7: ✓ | E7: ✓
A8: Morty | B8: Male | C8: ✓ | D8: ✗ | E8: ✗
A9: Ben | B9: Male | C9: ✗ | D9: ✓ | E9: ✗
A10: Bea | B10: Female | C10: ✓ | D10: ✗ | E10: ✗
A11: Bill Nye | B11: Male | C11: ✗ | D11: ✓ | E11: ✗
A12: Justin Trudeau | B12: Male | C12: ✗ | D12: ✓ | E12: ✗
A13: Katy Perry | B13: Female | C13: ✓ | D13: ✗ | E13: ✗
A14: House | B14: Male | C14: ✓ | D14: ✗ | E14: ✗
A15: Wilson | B15: Male | C15: ✓ | D15: ✗ | E15: ✗
A16: Cuddy | B16: Female | C16: ✓ | D16: ✗ | E16: ✗
A17: Cameron | B17: Female | C17: ✓ | D17: ✗ | E17: ✗
... A51: Alvie | B51: Male | C51: ✓ | D51: ✗ | E51: ✓

Sheet Relationship Analysis
A1: 🏝️ MII RELATIONSHIP ANALYSIS
A2: Optimal pairing to minimize Miis who fail to find a relationship
A4: 📊 POPULATION OVERVIEW
A5: Metric | B5: Count | C5: % of Total
A6: Total Miis | B6: =COUNTA('Mii List'!A2:A200) -> 50 | C6: —
A7: Males | B7: =COUNTIF('Mii List'!B2:B200,"Male") -> 32 | C7: =B7/B6 -> 0.64
A8: Females | B8: =COUNTIF('Mii List'!B2:B200,"Female") -> 16 | C8: =B8/B6 -> 0.32
A9: Enbies | B9: =COUNTIF('Mii List'!B2:B200,"Nonbinary") -> 2 | C9: =B9/B6 -> 0.04
A11: 💕 ATTRACTION PREFERENCES
A12: Preference | B12: Count | C12: % of Total
A13: Attracted to men | B13: =SUM('Matching Engine'!F2:F201) -> 33 | C13: =B13/B6 -> 0.66
A14: Attracted to women | B14: =SUM('Matching Engine'!G2:G201) -> 39 | C14: =B14/B6 -> 0.78
A15: Attracted to enbies | B15: =SUM('Matching Engine'!H2:H201) -> 24 | C15: =B15/B6 -> 0.48
A16: Attracted to nobody | B16: {=SUMPRODUCT(('Matching Engine'!A2:A201<>"")*('Matching Engine'!F2:F201=0)*('Matching Engine'!G2:G201=0)*('Matching Engine'!H2:H201=0))} -> 1 | C16: =B16/B6 -> 0.02
A18: 🔍 SUPPLY & DEMAND ANALYSIS
A19: Market | B19: Demand | C19: Supply | D19: Surplus (unpaired)
A20: ♂ wanting nobody | B20: =SUMPRODUCT(('Matching Engine'!I2:I201=1)*('Matching Engine'!F2:F201=0)*('Matching Engine'!G2:G201=0)*('Matching Engine'!H2:H201=0)) -> 0 | C20: 0 | D20: =MAX(0,B20-C20) -> 0
A21: ♂ wanting ⚧ only | B21: =SUMPRODUCT(('Matching Engine'!I2:I201=1)*('Matching Engine'!F2:F201=0)*('Matching Engine'!G2:G201=0)*('Matching Engine'!H2:H201=1)) -> 0 | C21: =SUMPRODUCT(('Matching Engine'!K2:K201=1)*('Matching Engine'!F2:F201=1)) -> 1 | D21: =MAX(0,B21-C21) -> 0
A22: ♂ wanting ♀ only | B22: =SUMPRODUCT(('Matching Engine'!I2:I201=1)*('Matching Engine'!F2:F201=0)*('Matching Engine'!G2:G201=1)*('Matching Engine'!H2:H201=0)) -> 13 | C22: =SUMPRODUCT(('Matching Engine'!J2:J201=1)*('Matching Engine'!F2:F201=1)) -> 14 | D22: =MAX(0,B22-C22) -> 0
A23: ♂ wanting ♀+⚧ | B23: =SUMPRODUCT(('Matching Engine'!I2:I201=1)*('Matching Engine'!F2:F201=0)*('Matching Engine'!G2:G201=1)*('Matching Engine'!H2:H201=1)) -> 1 | C23: =SUMPRODUCT(('Matching Engine'!J2:J201=1)*('Matching Engine'!F2:F201=1))+SUMPRODUCT(('Matching Engine'!K2:K201=1)*('Matching Engine'!F2:F201=1)) -> 15 | D23: =MAX(0,B23-C23) -> 0
A24: ♂ wanting ♂ only | B24: =SUMPRODUCT(('Matching Engine'!I2:I201=1)*('Matching Engine'!F2:F201=1)*('Matching Engine'!G2:G201=0)*('Matching Engine'!H2:H201=0)) -> 5 | C24: =SUMPRODUCT(('Matching Engine'!I2:I201=1)*('Matching Engine'!F2:F201=1)) -> 18 | D24: =MAX(0,B24-C24) -> 0
A25: ♂ wanting ♂+⚧ | B25: =SUMPRODUCT(('Matching Engine'!I2:I201=1)*('Matching Engine'!F2:F201=1)*('Matching Engine'!G2:G201=0)*('Matching Engine'!H2:H201=1)) -> 1 | C25: =SUMPRODUCT(('Matching Engine'!I2:I201=1)*('Matching Engine'!F2:F201=1))+SUMPRODUCT(('Matching Engine'!K2:K201=1)*('Matching Engine'!F2:F201=1)) -> 19 | D25: =MAX(0,B25-C25) -> 0
A26: ♂ wanting ♂+♀ | B26: =SUMPRODUCT(('Matching Engine'!I2:I201=1)*('Matching Engine'!F2:F201=1)*('Matching Engine'!G2:G201=1)*('Matching Engine'!H2:H201=0)) -> 0 | C26: =SUMPRODUCT(('Matching Engine'!I2:I201=1)*('Matching Engine'!F2:F201=1))+SUMPRODUCT(('Matching Engine'!J2:J201=1)*('Matching Engine'!F2:F201=1)) -> 32 | D26: =MAX(0,B26-C26) -> 0
A27: ♂ wanting ♂+♀+⚧ | B27: =SUMPRODUCT(('Matching Engine'!I2:I201=1)*('Matching Engine'!F2:F201=1)*('Matching Engine'!G2:G201=1)*('Matching Engine'!H2:H201=1)) -> 12 | C27: =SUMPRODUCT(('Matching Engine'!I2:I201=1)*('Matching Engine'!F2:F201=1))+SUMPRODUCT(('Matching Engine'!J2:J201=1)*('Matching Engine'!F2:F201=1))+SUMPRODUCT(('Matching Engine'!K2:K201=1)*('Matching Engine'!F2:F201=1)) -> 33 | D27: =MAX(0,B27-C27) -> 0
A28: ♀ wanting nobody | B28: =SUMPRODUCT(('Matching Engine'!J2:J201=1)*('Matching Engine'!F2:F201=0)*('Matching Engine'!G2:G201=0)*('Matching Engine'!H2:H201=0)) -> 0 | C28: 0 | D28: =MAX(0,B28-C28) -> 0
A29: ♀ wanting ⚧ only | B29: =SUMPRODUCT(('Matching Engine'!J2:J201=1)*('Matching Engine'!F2:F201=0)*('Matching Engine'!G2:G201=0)*('Matching Engine'!H2:H201=1)) -> 0 | C29: =SUMPRODUCT(('Matching Engine'!K2:K201=1)*('Matching Engine'!G2:G201=1)) -> 1 | D29: =MAX(0,B29-C29) -> 0
A30: ♀ wanting ♀ only | B30: =SUMPRODUCT(('Matching Engine'!J2:J201=1)*('Matching Engine'!F2:F201=0)*('Matching Engine'!G2:G201=1)*('Matching Engine'!H2:H201=0)) -> 2 | C30: =SUMPRODUCT(('Matching Engine'!J2:J201=1)*('Matching Engine'!G2:G201=1)) -> 12 | D30: =MAX(0,B30-C30) -> 0
A31: ♀ wanting ♀+⚧ | B31: =SUMPRODUCT(('Matching Engine'!J2:J201=1)*('Matching Engine'!F2:F201=0)*('Matching Engine'!G2:G201=1)*('Matching Engine'!H2:H201=1)) -> 0 | C31: =SUMPRODUCT(('Matching Engine'!J2:J201=1)*('Matching Engine'!G2:G201=1))+SUMPRODUCT(('Matching Engine'!K2:K201=1)*('Matching Engine'!G2:G201=1)) -> 13 | D31: =MAX(0,B31-C31) -> 0
A32: ♀ wanting ♂ only | B32: =SUMPRODUCT(('Matching Engine'!J2:J201=1)*('Matching Engine'!F2:F201=1)*('Matching Engine'!G2:G201=0)*('Matching Engine'!H2:H201=0)) -> 4 | C32: =SUMPRODUCT(('Matching Engine'!I2:I201=1)*('Matching Engine'!G2:G201=1)) -> 26 | D32: =MAX(0,B32-C32) -> 0
A33: ♀ wanting ♂+⚧ | B33: =SUMPRODUCT(('Matching Engine'!J2:J201=1)*('Matching Engine'!F2:F201=1)*('Matching Engine'!G2:G201=0)*('Matching Engine'!H2:H201=1)) -> 0 | C33: =SUMPRODUCT(('Matching Engine'!I2:I201=1)*('Matching Engine'!G2:G201=1))+SUMPRODUCT(('Matching Engine'!K2:K201=1)*('Matching Engine'!G2:G201=1)) -> 27 | D33: =MAX(0,B33-C33) -> 0
A34: ♀ wanting ♂+♀ | B34: =SUMPRODUCT(('Matching Engine'!J2:J201=1)*('Matching Engine'!F2:F201=1)*('Matching Engine'!G2:G201=1)*('Matching Engine'!H2:H201=0)) -> 1 | C34: =SUMPRODUCT(('Matching Engine'!I2:I201=1)*('Matching Engine'!G2:G201=1))+SUMPRODUCT(('Matching Engine'!J2:J201=1)*('Matching Engine'!G2:G201=1)) -> 38 | D34: =MAX(0,B34-C34) -> 0
A35: ♀ wanting ♂+♀+⚧ | B35: =SUMPRODUCT(('Matching Engine'!J2:J201=1)*('Matching Engine'!F2:F201=1)*('Matching Engine'!G2:G201=1)*('Matching Engine'!H2:H201=1)) -> 9 | C35: =SUMPRODUCT(('Matching Engine'!I2:I201=1)*('Matching Engine'!G2:G201=1))+SUMPRODUCT(('Matching Engine'!J2:J201=1)*('Matching Engine'!G2:G201=1))+SUMPRODUCT(('Matching Engine'!K2:K201=1)*('Matching Engine'!G2:G201=1)) -> 39 | D35: =MAX(0,B35-C35) -> 0
A36: ⚧ wanting nobody | B36: =SUMPRODUCT(('Matching Engine'!K2:K201=1)*('Matching Engine'!F2:F201=0)*('Matching Engine'!G2:G201=0)*('Matching Engine'!H2:H201=0)) -> 1 | C36: 0 | D36: =MAX(0,B36-C36) -> 1
A37: ⚧ wanting ⚧ only | B37: =SUMPRODUCT(('Matching Engine'!K2:K201=1)*('Matching Engine'!F2:F201=0)*('Matching Engine'!G2:G201=0)*('Matching Engine'!H2:H201=1)) -> 0 | C37: =SUMPRODUCT(('Matching Engine'!K2:K201=1)*('Matching Engine'!H2:H201=1)) -> 1 | D37: =MAX(0,B37-C37) -> 0
A38: ⚧ wanting ♀ only | B38: =SUMPRODUCT(('Matching Engine'!K2:K201=1)*('Matching Engine'!F2:F201=0)*('Matching Engine'!G2:G201=1)*('Matching Engine'!H2:H201=0)) -> 0 | C38: =SUMPRODUCT(('Matching Engine'!J2:J201=1)*('Matching Engine'!H2:H201=1)) -> 9 | D38: =MAX(0,B38-C38) -> 0
A39: ⚧ wanting ♀+⚧ | B39: =SUMPRODUCT(('Matching Engine'!K2:K201=1)*('Matching Engine'!F2:F201=0)*('Matching Engine'!G2:G201=1)*('Matching Engine'!H2:H201=1)) -> 0 | C39: =SUMPRODUCT(('Matching Engine'!J2:J201=1)*('Matching Engine'!H2:H201=1))+SUMPRODUCT(('Matching Engine'!K2:K201=1)*('Matching Engine'!H2:H201=1)) -> 10 | D39: =MAX(0,B39-C39) -> 0
A40: ⚧ wanting ♂ only | B40: =SUMPRODUCT(('Matching Engine'!K2:K201=1)*('Matching Engine'!F2:F201=1)*('Matching Engine'!G2:G201=0)*('Matching Engine'!H2:H201=0)) -> 0 | C40: =SUMPRODUCT(('Matching Engine'!I2:I201=1)*('Matching Engine'!H2:H201=1)) -> 14 | D40: =MAX(0,B40-C40) -> 0
A41: ⚧ wanting ♂+⚧ | B41: =SUMPRODUCT(('Matching Engine'!K2:K201=1)*('Matching Engine'!F2:F201=1)*('Matching Engine'!G2:G201=0)*('Matching Engine'!H2:H201=1)) -> 0 | C41: =SUMPRODUCT(('Matching Engine'!I2:I201=1)*('Matching Engine'!H2:H201=1))+SUMPRODUCT(('Matching Engine'!K2:K201=1)*('Matching Engine'!H2:H201=1)) -> 15 | D41: =MAX(0,B41-C41) -> 0
A42: ⚧ wanting ♂+♀ | B42: =SUMPRODUCT(('Matching Engine'!K2:K201=1)*('Matching Engine'!F2:F201=1)*('Matching Engine'!G2:G201=1)*('Matching Engine'!H2:H201=0)) -> 0 | C42: =SUMPRODUCT(('Matching Engine'!I2:I201=1)*('Matching Engine'!H2:H201=1))+SUMPRODUCT(('Matching Engine'!J2:J201=1)*('Matching Engine'!H2:H201=1)) -> 23 | D42: =MAX(0,B42-C42) -> 0
A43: ⚧ wanting ♂+♀+⚧ | B43: =SUMPRODUCT(('Matching Engine'!K2:K201=1)*('Matching Engine'!F2:F201=1)*('Matching Engine'!G2:G201=1)*('Matching Engine'!H2:H201=1)) -> 1 | C43: =SUMPRODUCT(('Matching Engine'!I2:I201=1)*('Matching Engine'!H2:H201=1))+SUMPRODUCT(('Matching Engine'!J2:J201=1)*('Matching Engine'!H2:H201=1))+SUMPRODUCT(('Matching Engine'!K2:K201=1)*('Matching Engine'!H2:H201=1)) -> 24 | D43: =MAX(0,B43-C43) -> 0
A46: ⚠️ MATCHING RESULTS
A47: Result | B47: Value | C47: Formula Logic
A48: Zero-Compatible (guaranteed alone) | B48: =SUMPRODUCT(('Matching Engine'!A2:A201<>"")*('Matching Engine'!L2:L201=0)) -> 1 | C48: Miis with 0 compatible partners
A49: Surplus from constrained markets | B49: =SUM(D21:D27,D29:D35,D37:D43) -> 0 | C49: Exclusive-preference Miis exceeding reciprocal supply
A50: Parity adjustment (odd total) | B50: =IF(MOD(B6-B48-B49,2)=1,1,0) -> 1 | C50: Odd remaining Miis → 1 extra unpaired
A51: 📛 MINIMUM UNPAIRED MIIS | B51: =B48+B49+B50 -> 2 | C51: zero-compatible + surplus + parity
A52: Maximum pairs formed | B52: =INT((B6-B51)/2) -> 24 | C52: (total - unpaired) / 2
A53: Maximum pairing success rate | B53: =(B6-B51)/B6 -> 0.96 | C53: Percentage who can find a partner
A54: Probable pairs formed | B54: {=_xlfn.LET(_xlpm.a,'Matching Engine'!N2:N51,_xlpm.b,'Matching Engine'!L2:L51,_xlpm.c,B6,_xlpm.s,'Matching Engine'!P2:P51,_xlpm.d,_xlpm.c/2,_xlpm.e,SUMPRODUCT(IF(_xlpm.b=0,1,EXP(-(_xlpm.a+_xlpm.b*_xlpm.s*_xlpm.d/_xlpm.c)))),_xlpm.f,(_xlpm.e+_xlpm.d)/2,_xlpm.g,SUMPRODUCT(IF(_xlpm.b=0,1,EXP(-(_xlpm.a+_xlpm.b*_xlpm.s*_xlpm.f/_xlpm.c)))),_xlpm.h,(_xlpm.g+_xlpm.f)/2,_xlpm.i,SUMPRODUCT(IF(_xlpm.b=0,1,EXP(-(_xlpm.a+_xlpm.b*_xlpm.s*_xlpm.h/_xlpm.c)))),_xlpm.j,(_xlpm.i+_xlpm.h)/2,_xlpm.k,SUMPRODUCT(IF(_xlpm.b=0,1,EXP(-(_xlpm.a+_xlpm.b*_xlpm.s*_xlpm.j/_xlpm.c)))),_xlpm.l,(_xlpm.k+_xlpm.j)/2,_xlpm.m,SUMPRODUCT(IF(_xlpm.b=0,1,EXP(-(_xlpm.a+_xlpm.b*_xlpm.s*_xlpm.l/_xlpm.c)))),_xlpm.n,(_xlpm.m+_xlpm.l)/2,(_xlpm.c-_xlpm.n)/2)} -> 21.555299 | C54: Greedy model: Miis pair with random compatible partners. Uses Poisson competition model with iterative pool depletion and competition-ratio correction for shared partner pools.
A55: Probable pairing success rate | B55: =B54*2/B6 -> 0.86221195 | C55: Percentage who find a compatible partner under greedy random matching
A57: WHO'S AT RISK? (0 Compatible Partners)
A58: Name | B58: Gender | C58: Preferences | D58: # compatible | E58: Reason
A59: {=IFERROR(INDEX('Matching Engine'!A$2:A$201,SMALL(IF('Matching Engine'!L$2:L$201=0,ROW('Matching Engine'!A$2:A$201)-ROW('Matching Engine'!A$2)+1),ROW()-ROW($A$59)+1)),"")} -> Nny | B59: =IF(A59="","",INDEX('Matching Engine'!B$2:B$201,MATCH(A59,'Matching Engine'!A$2:A$201,0))) -> Nonbinary | C59: =IF(A59="","",IF(AND(INDEX('Matching Engine'!F$2:F$201,MATCH(A59,'Matching Engine'!A$2:A$201,0))=0,INDEX('Matching Engine'!G$2:G$201,MATCH(A59,'Matching Engine'!A$2:A$201,0))=0,INDEX('Matching Engine'!H$2:H$201,MATCH(A59,'Matching Engine'!A$2:A$201,0))=0),"None",IF(INDEX('Matching Engine'!F$2:F$201,MATCH(A59,'Matching Engine'!A$2:A$201,0))=1,"♂ ","")&IF(INDEX('Matching Engine'!G$2:G$201,MATCH(A59,'Matching Engine'!A$2:A$201,0))=1,"♀ ","")&IF(INDEX('Matching Engine'!H$2:H$201,MATCH(A59,'Matching Engine'!A$2:A$201,0))=1,"⚧",""))) -> None | D59: =IF(A59="","",INDEX('Matching Engine'!L$2:L$201,MATCH(A59,'Matching Engine'!A$2:A$201,0))) -> 0 | E59: =IF(A59="","",IF(AND(INDEX('Matching Engine'!F$2:F$201,MATCH(A59,'Matching Engine'!A$2:A$201,0))=0,INDEX('Matching Engine'!G$2:G$201,MATCH(A59,'Matching Engine'!A$2:A$201,0))=0,INDEX('Matching Engine'!H$2:H$201,MATCH(A59,'Matching Engine'!A$2:A$201,0))=0),"Attracted to nobody","No reciprocal matches")) -> Attracted to nobody
A60: {=IFERROR(INDEX('Matching Engine'!A$2:A$201,SMALL(IF('Matching Engine'!L$2:L$201=0,ROW('Matching Engine'!A$2:A$201)-ROW('Matching Engine'!A$2)+1),ROW()-ROW($A$59)+1)),"")} | B60: =IF(A60="","",INDEX('Matching Engine'!B$2:B$201,MATCH(A60,'Matching Engine'!A$2:A$201,0))) | C60: =IF(A60="","",IF(AND(INDEX('Matching Engine'!F$2:F$201,MATCH(A60,'Matching Engine'!A$2:A$201,0))=0,INDEX('Matching Engine'!G$2:G$201,MATCH(A60,'Matching Engine'!A$2:A$201,0))=0,INDEX('Matching Engine'!H$2:H$201,MATCH(A60,'Matching Engine'!A$2:A$201,0))=0),"None",IF(INDEX('Matching Engine'!F$2:F$201,MATCH(A60,'Matching Engine'!A$2:A$201,0))=1,"♂ ","")&IF(INDEX('Matching Engine'!G$2:G$201,MATCH(A60,'Matching Engine'!A$2:A$201,0))=1,"♀ ","")&IF(INDEX('Matching Engine'!H$2:H$201,MATCH(A60,'Matching Engine'!A$2:A$201,0))=1,"⚧",""))) | D60: =IF(A60="","",INDEX('Matching Engine'!L$2:L$201,MATCH(A60,'Matching Engine'!A$2:A$201,0))) | E60: =IF(A60="","",IF(AND(INDEX('Matching Engine'!F$2:F$201,MATCH(A60,'Matching Engine'!A$2:A$201,0))=0,INDEX('Matching Engine'!G$2:G$201,MATCH(A60,'Matching Engine'!A$2:A$201,0))=0,INDEX('Matching Engine'!H$2:H$201,MATCH(A60,'Matching Engine'!A$2:A$201,0))=0),"Attracted to nobody","No reciprocal matches"))
A61: {=IFERROR(INDEX('Matching Engine'!A$2:A$201,SMALL(IF('Matching Engine'!L$2:L$201=0,ROW('Matching Engine'!A$2:A$201)-ROW('Matching Engine'!A$2)+1),ROW()-ROW($A$59)+1)),"")} | B61: =IF(A61="","",INDEX('Matching Engine'!B$2:B$201,MATCH(A61,'Matching Engine'!A$2:A$201,0))) | C61: =IF(A61="","",IF(AND(INDEX('Matching Engine'!F$2:F$201,MATCH(A61,'Matching Engine'!A$2:A$201,0))=0,INDEX('Matching Engine'!G$2:G$201,MATCH(A61,'Matching Engine'!A$2:A$201,0))=0,INDEX('Matching Engine'!H$2:H$201,MATCH(A61,'Matching Engine'!A$2:A$201,0))=0),"None",IF(INDEX('Matching Engine'!F$2:F$201,MATCH(A61,'Matching Engine'!A$2:A$201,0))=1,"♂ ","")&IF(INDEX('Matching Engine'!G$2:G$201,MATCH(A61,'Matching Engine'!A$2:A$201,0))=1,"♀ ","")&IF(INDEX('Matching Engine'!H$2:H$201,MATCH(A61,'Matching Engine'!A$2:A$201,0))=1,"⚧",""))) | D61: =IF(A61="","",INDEX('Matching Engine'!L$2:L$201,MATCH(A61,'Matching Engine'!A$2:A$201,0))) | E61: =IF(A61="","",IF(AND(INDEX('Matching Engine'!F$2:F$201,MATCH(A61,'Matching Engine'!A$2:A$201,0))=0,INDEX('Matching Engine'!G$2:G$201,MATCH(A61,'Matching Engine'!A$2:A$201,0))=0,INDEX('Matching Engine'!H$2:H$201,MATCH(A61,'Matching Engine'!A$2:A$201,0))=0),"Attracted to nobody","No reciprocal matches"))
A62: {=IFERROR(INDEX('Matching Engine'!A$2:A$201,SMALL(IF('Matching Engine'!L$2:L$201=0,ROW('Matching Engine'!A$2:A$201)-ROW('Matching Engine'!A$2)+1),ROW()-ROW($A$59)+1)),"")} | B62: =IF(A62="","",INDEX('Matching Engine'!B$2:B$201,MATCH(A62,'Matching Engine'!A$2:A$201,0))) | C62: =IF(A62="","",IF(AND(INDEX('Matching Engine'!F$2:F$201,MATCH(A62,'Matching Engine'!A$2:A$201,0))=0,INDEX('Matching Engine'!G$2:G$201,MATCH(A62,'Matching Engine'!A$2:A$201,0))=0,INDEX('Matching Engine'!H$2:H$201,MATCH(A62,'Matching Engine'!A$2:A$201,0))=0),"None",IF(INDEX('Matching Engine'!F$2:F$201,MATCH(A62,'Matching Engine'!A$2:A$201,0))=1,"♂ ","")&IF(INDEX('Matching Engine'!G$2:G$201,MATCH(A62,'Matching Engine'!A$2:A$201,0))=1,"♀ ","")&IF(INDEX('Matching Engine'!H$2:H$201,MATCH(A62,'Matching Engine'!A$2:A$201,0))=1,"⚧",""))) | D62: =IF(A62="","",INDEX('Matching Engine'!L$2:L$201,MATCH(A62,'Matching Engine'!A$2:A$201,0))) | E62: =IF(A62="","",IF(AND(INDEX('Matching Engine'!F$2:F$201,MATCH(A62,'Matching Engine'!A$2:A$201,0))=0,INDEX('Matching Engine'!G$2:G$201,MATCH(A62,'Matching Engine'!A$2:A$201,0))=0,INDEX('Matching Engine'!H$2:H$201,MATCH(A62,'Matching Engine'!A$2:A$201,0))=0),"Attracted to nobody","No reciprocal matches"))
A63: {=IFERROR(INDEX('Matching Engine'!A$2:A$201,SMALL(IF('Matching Engine'!L$2:L$201=0,ROW('Matching Engine'!A$2:A$201)-ROW('Matching Engine'!A$2)+1),ROW()-ROW($A$59)+1)),"")} | B63: =IF(A63="","",INDEX('Matching Engine'!B$2:B$201,MATCH(A63,'Matching Engine'!A$2:A$201,0))) | C63: =IF(A63="","",IF(AND(INDEX('Matching Engine'!F$2:F$201,MATCH(A63,'Matching Engine'!A$2:A$201,0))=0,INDEX('Matching Engine'!G$2:G$201,MATCH(A63,'Matching Engine'!A$2:A$201,0))=0,INDEX('Matching Engine'!H$2:H$201,MATCH(A63,'Matching Engine'!A$2:A$201,0))=0),"None",IF(INDEX('Matching Engine'!F$2:F$201,MATCH(A63,'Matching Engine'!A$2:A$201,0))=1,"♂ ","")&IF(INDEX('Matching Engine'!G$2:G$201,MATCH(A63,'Matching Engine'!A$2:A$201,0))=1,"♀ ","")&IF(INDEX('Matching Engine'!H$2:H$201,MATCH(A63,'Matching Engine'!A$2:A$201,0))=1,"⚧",""))) | D63: =IF(A63="","",INDEX('Matching Engine'!L$2:L$201,MATCH(A63,'Matching Engine'!A$2:A$201,0))) | E63: =IF(A63="","",IF(AND(INDEX('Matching Engine'!F$2:F$201,MATCH(A63,'Matching Engine'!A$2:A$201,0))=0,INDEX('Matching Engine'!G$2:G$201,MATCH(A63,'Matching Engine'!A$2:A$201,0))=0,INDEX('Matching Engine'!H$2:H$201,MATCH(A63,'Matching Engine'!A$2:A$201,0))=0),"Attracted to nobody","No reciprocal matches"))
A64: {=IFERROR(INDEX('Matching Engine'!A$2:A$201,SMALL(IF('Matching Engine'!L$2:L$201=0,ROW('Matching Engine'!A$2:A$201)-ROW('Matching Engine'!A$2)+1),ROW()-ROW($A$59)+1)),"")} | B64: =IF(A64="","",INDEX('Matching Engine'!B$2:B$201,MATCH(A64,'Matching Engine'!A$2:A$201,0))) | C64: =IF(A64="","",IF(AND(INDEX('Matching Engine'!F$2:F$201,MATCH(A64,'Matching Engine'!A$2:A$201,0))=0,INDEX('Matching Engine'!G$2:G$201,MATCH(A64,'Matching Engine'!A$2:A$201,0))=0,INDEX('Matching Engine'!H$2:H$201,MATCH(A64,'Matching Engine'!A$2:A$201,0))=0),"None",IF(INDEX('Matching Engine'!F$2:F$201,MATCH(A64,'Matching Engine'!A$2:A$201,0))=1,"♂ ","")&IF(INDEX('Matching Engine'!G$2:G$201,MATCH(A64,'Matching Engine'!A$2:A$201,0))=1,"♀ ","")&IF(INDEX('Matching Engine'!H$2:H$201,MATCH(A64,'Matching Engine'!A$2:A$201,0))=1,"⚧",""))) | D64: =IF(A64="","",INDEX('Matching Engine'!L$2:L$201,MATCH(A64,'Matching Engine'!A$2:A$201,0))) | E64: =IF(A64="","",IF(AND(INDEX('Matching Engine'!F$2:F$201,MATCH(A64,'Matching Engine'!A$2:A$201,0))=0,INDEX('Matching Engine'!G$2:G$201,MATCH(A64,'Matching Engine'!A$2:A$201,0))=0,INDEX('Matching Engine'!H$2:H$201,MATCH(A64,'Matching Engine'!A$2:A$201,0))=0),"Attracted to nobody","No reciprocal matches"))
A65: {=IFERROR(INDEX('Matching Engine'!A$2:A$201,SMALL(IF('Matching Engine'!L$2:L$201=0,ROW('Matching Engine'!A$2:A$201)-ROW('Matching Engine'!A$2)+1),ROW()-ROW($A$59)+1)),"")} | B65: =IF(A65="","",INDEX('Matching Engine'!B$2:B$201,MATCH(A65,'Matching Engine'!A$2:A$201,0))) | C65: =IF(A65="","",IF(AND(INDEX('Matching Engine'!F$2:F$201,MATCH(A65,'Matching Engine'!A$2:A$201,0))=0,INDEX('Matching Engine'!G$2:G$201,MATCH(A65,'Matching Engine'!A$2:A$201,0))=0,INDEX('Matching Engine'!H$2:H$201,MATCH(A65,'Matching Engine'!A$2:A$201,0))=0),"None",IF(INDEX('Matching Engine'!F$2:F$201,MATCH(A65,'Matching Engine'!A$2:A$201,0))=1,"♂ ","")&IF(INDEX('Matching Engine'!G$2:G$201,MATCH(A65,'Matching Engine'!A$2:A$201,0))=1,"♀ ","")&IF(INDEX('Matching Engine'!H$2:H$201,MATCH(A65,'Matching Engine'!A$2:A$201,0))=1,"⚧",""))) | D65: =IF(A65="","",INDEX('Matching Engine'!L$2:L$201,MATCH(A65,'Matching Engine'!A$2:A$201,0))) | E65: =IF(A65="","",IF(AND(INDEX('Matching Engine'!F$2:F$201,MATCH(A65,'Matching Engine'!A$2:A$201,0))=0,INDEX('Matching Engine'!G$2:G$201,MATCH(A65,'Matching Engine'!A$2:A$201,0))=0,INDEX('Matching Engine'!H$2:H$201,MATCH(A65,'Matching Engine'!A$2:A$201,0))=0),"Attracted to nobody","No reciprocal matches"))
B66: =IF(A66="","",INDEX('Matching Engine'!B$2:B$201,MATCH(A66,'Matching Engine'!A$2:A$201,0))) | C66: =IF(A66="","",IF(AND(INDEX('Matching Engine'!F$2:F$201,MATCH(A66,'Matching Engine'!A$2:A$201,0))=0,INDEX('Matching Engine'!G$2:G$201,MATCH(A66,'Matching Engine'!A$2:A$201,0))=0,INDEX('Matching Engine'!H$2:H$201,MATCH(A66,'Matching Engine'!A$2:A$201,0))=0),"None",IF(INDEX('Matching Engine'!F$2:F$201,MATCH(A66,'Matching Engine'!A$2:A$201,0))=1,"♂ ","")&IF(INDEX('Matching Engine'!G$2:G$201,MATCH(A66,'Matching Engine'!A$2:A$201,0))=1,"♀ ","")&IF(INDEX('Matching Engine'!H$2:H$201,MATCH(A66,'Matching Engine'!A$2:A$201,0))=1,"⚧",""))) | D66: =IF(A66="","",0) | E66: =IF(A66="","",IF(AND(INDEX('Matching Engine'!F$2:F$201,MATCH(A66,'Matching Engine'!A$2:A$201,0))=0,INDEX('Matching Engine'!G$2:G$201,MATCH(A66,'Matching Engine'!A$2:A$201,0))=0,INDEX('Matching Engine'!H$2:H$201,MATCH(A66,'Matching Engine'!A$2:A$201,0))=0),"Attracted to nobody","No reciprocal matches"))
B67: =IF(A67="","",INDEX('Matching Engine'!B$2:B$201,MATCH(A67,'Matching Engine'!A$2:A$201,0))) | C67: =IF(A67="","",IF(AND(INDEX('Matching Engine'!F$2:F$201,MATCH(A67,'Matching Engine'!A$2:A$201,0))=0,INDEX('Matching Engine'!G$2:G$201,MATCH(A67,'Matching Engine'!A$2:A$201,0))=0,INDEX('Matching Engine'!H$2:H$201,MATCH(A67,'Matching Engine'!A$2:A$201,0))=0),"None",IF(INDEX('Matching Engine'!F$2:F$201,MATCH(A67,'Matching Engine'!A$2:A$201,0))=1,"♂ ","")&IF(INDEX('Matching Engine'!G$2:G$201,MATCH(A67,'Matching Engine'!A$2:A$201,0))=1,"♀ ","")&IF(INDEX('Matching Engine'!H$2:H$201,MATCH(A67,'Matching Engine'!A$2:A$201,0))=1,"⚧",""))) | D67: =IF(A67="","",0) | E67: =IF(A67="","",IF(AND(INDEX('Matching Engine'!F$2:F$201,MATCH(A67,'Matching Engine'!A$2:A$201,0))=0,INDEX('Matching Engine'!G$2:G$201,MATCH(A67,'Matching Engine'!A$2:A$201,0))=0,INDEX('Matching Engine'!H$2:H$201,MATCH(A67,'Matching Engine'!A$2:A$201,0))=0),"Attracted to nobody","No reciprocal matches"))
B68: =IF(A68="","",INDEX('Matching Engine'!B$2:B$201,MATCH(A68,'Matching Engine'!A$2:A$201,0))) | C68: =IF(A68="","",IF(AND(INDEX('Matching Engine'!F$2:F$201,MATCH(A68,'Matching Engine'!A$2:A$201,0))=0,INDEX('Matching Engine'!G$2:G$201,MATCH(A68,'Matching Engine'!A$2:A$201,0))=0,INDEX('Matching Engine'!H$2:H$201,MATCH(A68,'Matching Engine'!A$2:A$201,0))=0),"None",IF(INDEX('Matching Engine'!F$2:F$201,MATCH(A68,'Matching Engine'!A$2:A$201,0))=1,"♂ ","")&IF(INDEX('Matching Engine'!G$2:G$201,MATCH(A68,'Matching Engine'!A$2:A$201,0))=1,"♀ ","")&IF(INDEX('Matching Engine'!H$2:H$201,MATCH(A68,'Matching Engine'!A$2:A$201,0))=1,"⚧",""))) | D68: =IF(A68="","",0) | E68: =IF(A68="","",IF(AND(INDEX('Matching Engine'!F$2:F$201,MATCH(A68,'Matching Engine'!A$2:A$201,0))=0,INDEX('Matching Engine'!G$2:G$201,MATCH(A68,'Matching Engine'!A$2:A$201,0))=0,INDEX('Matching Engine'!H$2:H$201,MATCH(A68,'Matching Engine'!A$2:A$201,0))=0),"Attracted to nobody","No reciprocal matches"))
A70: FULL COMPATIBILITY ROSTER
A71: Name | B71: Gender | C71: Preferences | D71: # compatible | E71: Percentage of Miis compatible
A72: =IFERROR(INDEX('Matching Engine'!A$2:A$201,MATCH(ROW()-71,'Matching Engine'!M$2:M$201,0)),"") -> Nny | B72: =IF(A72="","",INDEX('Matching Engine'!B$2:B$201,MATCH(A72,'Matching Engine'!A$2:A$201,0))) -> Nonbinary | C72: =IF(A72="","",IF(AND(INDEX('Matching Engine'!F$2:F$201,MATCH(A72,'Matching Engine'!A$2:A$201,0))=0,INDEX('Matching Engine'!G$2:G$201,MATCH(A72,'Matching Engine'!A$2:A$201,0))=0,INDEX('Matching Engine'!H$2:H$201,MATCH(A72,'Matching Engine'!A$2:A$201,0))=0),"None",IF(INDEX('Matching Engine'!F$2:F$201,MATCH(A72,'Matching Engine'!A$2:A$201,0))=1,"♂ ","")&IF(INDEX('Matching Engine'!G$2:G$201,MATCH(A72,'Matching Engine'!A$2:A$201,0))=1,"♀ ","")&IF(INDEX('Matching Engine'!H$2:H$201,MATCH(A72,'Matching Engine'!A$2:A$201,0))=1,"⚧",""))) -> None | D72: =IF(A72="","",INDEX('Matching Engine'!L$2:L$201,MATCH(A72,'Matching Engine'!A$2:A$201,0))) -> 0 | E72: =IF(A72="","",IF(D72=0,"0% — no compatible partners",TEXT(D72/($B$6-1),"0%")&" — "&D72&" of "&($B$6-1)&" compatible")) -> 0% — no compatible partners
A73: =IFERROR(INDEX('Matching Engine'!A$2:A$201,MATCH(ROW()-71,'Matching Engine'!M$2:M$201,0)),"") -> Kanaya Maryam | B73: =IF(A73="","",INDEX('Matching Engine'!B$2:B$201,MATCH(A73,'Matching Engine'!A$2:A$201,0))) -> Female | C73: =IF(A73="","",IF(AND(INDEX('Matching Engine'!F$2:F$201,MATCH(A73,'Matching Engine'!A$2:A$201,0))=0,INDEX('Matching Engine'!G$2:G$201,MATCH(A73,'Matching Engine'!A$2:A$201,0))=0,INDEX('Matching Engine'!H$2:H$201,MATCH(A73,'Matching Engine'!A$2:A$201,0))=0),"None",IF(INDEX('Matching Engine'!F$2:F$201,MATCH(A73,'Matching Engine'!A$2:A$201,0))=1,"♂ ","")&IF(INDEX('Matching Engine'!G$2:G$201,MATCH(A73,'Matching Engine'!A$2:A$201,0))=1,"♀ ","")&IF(INDEX('Matching Engine'!H$2:H$201,MATCH(A73,'Matching Engine'!A$2:A$201,0))=1,"⚧",""))) -> ♀ | D73: =IF(A73="","",INDEX('Matching Engine'!L$2:L$201,MATCH(A73,'Matching Engine'!A$2:A$201,0))) -> 11 | E73: =IF(A73="","",IF(D73=0,"0% — no compatible partners",TEXT(D73/($B$6-1),"0%")&" — "&D73&" of "&($B$6-1)&" compatible")) -> 22% — 11 of 49 compatible
A74: =IFERROR(INDEX('Matching Engine'!A$2:A$201,MATCH(ROW()-71,'Matching Engine'!M$2:M$201,0)),"") -> Rose Lalonde | B74: =IF(A74="","",INDEX('Matching Engine'!B$2:B$201,MATCH(A74,'Matching Engine'!A$2:A$201,0))) -> Female | C74: =IF(A74="","",IF(AND(INDEX('Matching Engine'!F$2:F$201,MATCH(A74,'Matching Engine'!A$2:A$201,0))=0,INDEX('Matching Engine'!G$2:G$201,MATCH(A74,'Matching Engine'!A$2:A$201,0))=0,INDEX('Matching Engine'!H$2:H$201,MATCH(A74,'Matching Engine'!A$2:A$201,0))=0),"None",IF(INDEX('Matching Engine'!F$2:F$201,MATCH(A74,'Matching Engine'!A$2:A$201,0))=1,"♂ ","")&IF(INDEX('Matching Engine'!G$2:G$201,MATCH(A74,'Matching Engine'!A$2:A$201,0))=1,"♀ ","")&IF(INDEX('Matching Engine'!H$2:H$201,MATCH(A74,'Matching Engine'!A$2:A$201,0))=1,"⚧",""))) -> ♀ | D74: =IF(A74="","",INDEX('Matching Engine'!L$2:L$201,MATCH(A74,'Matching Engine'!A$2:A$201,0))) -> 11 | E74: =IF(A74="","",IF(D74=0,"0% — no compatible partners",TEXT(D74/($B$6-1),"0%")&" — "&D74&" of "&($B$6-1)&" compatible")) -> 22% — 11 of 49 compatible
A75: =IFERROR(INDEX('Matching Engine'!A$2:A$201,MATCH(ROW()-71,'Matching Engine'!M$2:M$201,0)),"") -> Barack Obama | B75: =IF(A75="","",INDEX('Matching Engine'!B$2:B$201,MATCH(A75,'Matching Engine'!A$2:A$201,0))) -> Male | C75: =IF(A75="","",IF(AND(INDEX('Matching Engine'!F$2:F$201,MATCH(A75,'Matching Engine'!A$2:A$201,0))=0,INDEX('Matching Engine'!G$2:G$201,MATCH(A75,'Matching Engine'!A$2:A$201,0))=0,INDEX('Matching Engine'!H$2:H$201,MATCH(A75,'Matching Engine'!A$2:A$201,0))=0),"None",IF(INDEX('Matching Engine'!F$2:F$201,MATCH(A75,'Matching Engine'!A$2:A$201,0))=1,"♂ ","")&IF(INDEX('Matching Engine'!G$2:G$201,MATCH(A75,'Matching Engine'!A$2:A$201,0))=1,"♀ ","")&IF(INDEX('Matching Engine'!H$2:H$201,MATCH(A75,'Matching Engine'!A$2:A$201,0))=1,"⚧",""))) -> ♀ | D75: =IF(A75="","",INDEX('Matching Engine'!L$2:L$201,MATCH(A75,'Matching Engine'!A$2:A$201,0))) -> 14 | E75: =IF(A75="","",IF(D75=0,"0% — no compatible partners",TEXT(D75/($B$6-1),"0%")&" — "&D75&" of "&($B$6-1)&" compatible")) -> 29% — 14 of 49 compatible
A76: =IFERROR(INDEX('Matching Engine'!A$2:A$201,MATCH(ROW()-71,'Matching Engine'!M$2:M$201,0)),"") -> Ben | B76: =IF(A76="","",INDEX('Matching Engine'!B$2:B$201,MATCH(A76,'Matching Engine'!A$2:A$201,0))) -> Male | C76: =IF(A76="","",IF(AND(INDEX('Matching Engine'!F$2:F$201,MATCH(A76,'Matching Engine'!A$2:A$201,0))=0,INDEX('Matching Engine'!G$2:G$201,MATCH(A76,'Matching Engine'!A$2:A$201,0))=0,INDEX('Matching Engine'!H$2:H$201,MATCH(A76,'Matching Engine'!A$2:A$201,0))=0),"None",IF(INDEX('Matching Engine'!F$2:F$201,MATCH(A76,'Matching Engine'!A$2:A$201,0))=1,"♂ ","")&IF(INDEX('Matching Engine'!G$2:G$201,MATCH(A76,'Matching Engine'!A$2:A$201,0))=1,"♀ ","")&IF(INDEX('Matching Engine'!H$2:H$201,MATCH(A76,'Matching Engine'!A$2:A$201,0))=1,"⚧",""))) -> ♀ | D76: =IF(A76="","",INDEX('Matching Engine'!L$2:L$201,MATCH(A76,'Matching Engine'!A$2:A$201,0))) -> 14 | E76: =IF(A76="","",IF(D76=0,"0% — no compatible partners",TEXT(D76/($B$6-1),"0%")&" — "&D76&" of "&($B$6-1)&" compatible")) -> 29% — 14 of 49 compatible
A77: =IFERROR(INDEX('Matching Engine'!A$2:A$201,MATCH(ROW()-71,'Matching Engine'!M$2:M$201,0)),"") -> Biff Williams | B77: =IF(A77="","",INDEX('Matching Engine'!B$2:B$201,MATCH(A77,'Matching Engine'!A$2:A$201,0))) -> Male | C77: =IF(A77="","",IF(AND(INDEX('Matching Engine'!F$2:F$201,MATCH(A77,'Matching Engine'!A$2:A$201,0))=0,INDEX('Matching Engine'!G$2:G$201,MATCH(A77,'Matching Engine'!A$2:A$201,0))=0,INDEX('Matching Engine'!H$2:H$201,MATCH(A77,'Matching Engine'!A$2:A$201,0))=0),"None",IF(INDEX('Matching Engine'!F$2:F$201,MATCH(A77,'Matching Engine'!A$2:A$201,0))=1,"♂ ","")&IF(INDEX('Matching Engine'!G$2:G$201,MATCH(A77,'Matching Engine'!A$2:A$201,0))=1,"♀ ","")&IF(INDEX('Matching Engine'!H$2:H$201,MATCH(A77,'Matching Engine'!A$2:A$201,0))=1,"⚧",""))) -> ♀ | D77: =IF(A77="","",INDEX('Matching Engine'!L$2:L$201,MATCH(A77,'Matching Engine'!A$2:A$201,0))) -> 14 | E77: =IF(A77="","",IF(D77=0,"0% — no compatible partners",TEXT(D77/($B$6-1),"0%")&" — "&D77&" of "&($B$6-1)&" compatible")) -> 29% — 14 of 49 compatible
A78: =IFERROR(INDEX('Matching Engine'!A$2:A$201,MATCH(ROW()-71,'Matching Engine'!M$2:M$201,0)),"") -> Bill Nye | B78: =IF(A78="","",INDEX('Matching Engine'!B$2:B$201,MATCH(A78,'Matching Engine'!A$2:A$201,0))) -> Male | C78: =IF(A78="","",IF(AND(INDEX('Matching Engine'!F$2:F$201,MATCH(A78,'Matching Engine'!A$2:A$201,0))=0,INDEX('Matching Engine'!G$2:G$201,MATCH(A78,'Matching Engine'!A$2:A$201,0))=0,INDEX('Matching Engine'!H$2:H$201,MATCH(A78,'Matching Engine'!A$2:A$201,0))=0),"None",IF(INDEX('Matching Engine'!F$2:F$201,MATCH(A78,'Matching Engine'!A$2:A$201,0))=1,"♂ ","")&IF(INDEX('Matching Engine'!G$2:G$201,MATCH(A78,'Matching Engine'!A$2:A$201,0))=1,"♀ ","")&IF(INDEX('Matching Engine'!H$2:H$201,MATCH(A78,'Matching Engine'!A$2:A$201,0))=1,"⚧",""))) -> ♀ | D78: =IF(A78="","",INDEX('Matching Engine'!L$2:L$201,MATCH(A78,'Matching Engine'!A$2:A$201,0))) -> 14 | E78: =IF(A78="","",IF(D78=0,"0% — no compatible partners",TEXT(D78/($B$6-1),"0%")&" — "&D78&" of "&($B$6-1)&" compatible")) -> 29% — 14 of 49 compatible
A79: =IFERROR(INDEX('Matching Engine'!A$2:A$201,MATCH(ROW()-71,'Matching Engine'!M$2:M$201,0)),"") -> Bill Trinnen | B79: =IF(A79="","",INDEX('Matching Engine'!B$2:B$201,MATCH(A79,'Matching Engine'!A$2:A$201,0))) -> Male | C79: =IF(A79="","",IF(AND(INDEX('Matching Engine'!F$2:F$201,MATCH(A79,'Matching Engine'!A$2:A$201,0))=0,INDEX('Matching Engine'!G$2:G$201,MATCH(A79,'Matching Engine'!A$2:A$201,0))=0,INDEX('Matching Engine'!H$2:H$201,MATCH(A79,'Matching Engine'!A$2:A$201,0))=0),"None",IF(INDEX('Matching Engine'!F$2:F$201,MATCH(A79,'Matching Engine'!A$2:A$201,0))=1,"♂ ","")&IF(INDEX('Matching Engine'!G$2:G$201,MATCH(A79,'Matching Engine'!A$2:A$201,0))=1,"♀ ","")&IF(INDEX('Matching Engine'!H$2:H$201,MATCH(A79,'Matching Engine'!A$2:A$201,0))=1,"⚧",""))) -> ♀ | D79: =IF(A79="","",INDEX('Matching Engine'!L$2:L$201,MATCH(A79,'Matching Engine'!A$2:A$201,0))) -> 14 | E79: =IF(A79="","",IF(D79=0,"0% — no compatible partners",TEXT(D79/($B$6-1),"0%")&" — "&D79&" of "&($B$6-1)&" compatible")) -> 29% — 14 of 49 compatible
A80: =IFERROR(INDEX('Matching Engine'!A$2:A$201,MATCH(ROW()-71,'Matching Engine'!M$2:M$201,0)),"") -> Foreman | B80: =IF(A80="","",INDEX('Matching Engine'!B$2:B$201,MATCH(A80,'Matching Engine'!A$2:A$201,0))) -> Male | C80: =IF(A80="","",IF(AND(INDEX('Matching Engine'!F$2:F$201,MATCH(A80,'Matching Engine'!A$2:A$201,0))=0,INDEX('Matching Engine'!G$2:G$201,MATCH(A80,'Matching Engine'!A$2:A$201,0))=0,INDEX('Matching Engine'!H$2:H$201,MATCH(A80,'Matching Engine'!A$2:A$201,0))=0),"None",IF(INDEX('Matching Engine'!F$2:F$201,MATCH(A80,'Matching Engine'!A$2:A$201,0))=1,"♂ ","")&IF(INDEX('Matching Engine'!G$2:G$201,MATCH(A80,'Matching Engine'!A$2:A$201,0))=1,"♀ ","")&IF(INDEX('Matching Engine'!H$2:H$201,MATCH(A80,'Matching Engine'!A$2:A$201,0))=1,"⚧",""))) -> ♀ | D80: =IF(A80="","",INDEX('Matching Engine'!L$2:L$201,MATCH(A80,'Matching Engine'!A$2:A$201,0))) -> 14 | E80: =IF(A80="","",IF(D80=0,"0% — no compatible partners",TEXT(D80/($B$6-1),"0%")&" — "&D80&" of "&($B$6-1)&" compatible")) -> 29% — 14 of 49 compatible
A81: =IFERROR(INDEX('Matching Engine'!A$2:A$201,MATCH(ROW()-71,'Matching Engine'!M$2:M$201,0)),"") -> Justin Trudeau | B81: =IF(A81="","",INDEX('Matching Engine'!B$2:B$201,MATCH(A81,'Matching Engine'!A$2:A$201,0))) -> Male | C81: =IF(A81="","",IF(AND(INDEX('Matching Engine'!F$2:F$201,MATCH(A81,'Matching Engine'!A$2:A$201,0))=0,INDEX('Matching Engine'!G$2:G$201,MATCH(A81,'Matching Engine'!A$2:A$201,0))=0,INDEX('Matching Engine'!H$2:H$201,MATCH(A81,'Matching Engine'!A$2:A$201,0))=0),"None",IF(INDEX('Matching Engine'!F$2:F$201,MATCH(A81,'Matching Engine'!A$2:A$201,0))=1,"♂ ","")&IF(INDEX('Matching Engine'!G$2:G$201,MATCH(A81,'Matching Engine'!A$2:A$201,0))=1,"♀ ","")&IF(INDEX('Matching Engine'!H$2:H$201,MATCH(A81,'Matching Engine'!A$2:A$201,0))=1,"⚧",""))) -> ♀ | D81: =IF(A81="","",INDEX('Matching Engine'!L$2:L$201,MATCH(A81,'Matching Engine'!A$2:A$201,0))) -> 14 | E81: =IF(A81="","",IF(D81=0,"0% — no compatible partners",TEXT(D81/($B$6-1),"0%")&" — "&D81&" of "&($B$6-1)&" compatible")) -> 29% — 14 of 49 compatible
A82: =IFERROR(INDEX('Matching Engine'!A$2:A$201,MATCH(ROW()-71,'Matching Engine'!M$2:M$201,0)),"") -> Kutner | B82: =IF(A82="","",INDEX('Matching Engine'!B$2:B$201,MATCH(A82,'Matching Engine'!A$2:A$201,0))) -> Male | C82: =IF(A82="","",IF(AND(INDEX('Matching Engine'!F$2:F$201,MATCH(A82,'Matching Engine'!A$2:A$201,0))=0,INDEX('Matching Engine'!G$2:G$201,MATCH(A82,'Matching Engine'!A$2:A$201,0))=0,INDEX('Matching Engine'!H$2:H$201,MATCH(A82,'Matching Engine'!A$2:A$201,0))=0),"None",IF(INDEX('Matching Engine'!F$2:F$201,MATCH(A82,'Matching Engine'!A$2:A$201,0))=1,"♂ ","")&IF(INDEX('Matching Engine'!G$2:G$201,MATCH(A82,'Matching Engine'!A$2:A$201,0))=1,"♀ ","")&IF(INDEX('Matching Engine'!H$2:H$201,MATCH(A82,'Matching Engine'!A$2:A$201,0))=1,"⚧",""))) -> ♀ | D82: =IF(A82="","",INDEX('Matching Engine'!L$2:L$201,MATCH(A82,'Matching Engine'!A$2:A$201,0))) -> 14 | E82: =IF(A82="","",IF(D82=0,"0% — no compatible partners",TEXT(D82/($B$6-1),"0%")&" — "&D82&" of "&($B$6-1)&" compatible")) -> 29% — 14 of 49 compatible
A83: =IFERROR(INDEX('Matching Engine'!A$2:A$201,MATCH(ROW()-71,'Matching Engine'!M$2:M$201,0)),"") -> Riley Freeman | B83: =IF(A83="","",INDEX('Matching Engine'!B$2:B$201,MATCH(A83,'Matching Engine'!A$2:A$201,0))) -> Male | C83: =IF(A83="","",IF(AND(INDEX('Matching Engine'!F$2:F$201,MATCH(A83,'Matching Engine'!A$2:A$201,0))=0,INDEX('Matching Engine'!G$2:G$201,MATCH(A83,'Matching Engine'!A$2:A$201,0))=0,INDEX('Matching Engine'!H$2:H$201,MATCH(A83,'Matching Engine'!A$2:A$201,0))=0),"None",IF(INDEX('Matching Engine'!F$2:F$201,MATCH(A83,'Matching Engine'!A$2:A$201,0))=1,"♂ ","")&IF(INDEX('Matching Engine'!G$2:G$201,MATCH(A83,'Matching Engine'!A$2:A$201,0))=1,"♀ ","")&IF(INDEX('Matching Engine'!H$2:H$201,MATCH(A83,'Matching Engine'!A$2:A$201,0))=1,"⚧",""))) -> ♀ | D83: =IF(A83="","",INDEX('Matching Engine'!L$2:L$201,MATCH(A83,'Matching Engine'!A$2:A$201,0))) -> 14 | E83: =IF(A83="","",IF(D83=0,"0% — no compatible partners",TEXT(D83/($B$6-1),"0%")&" — "&D83&" of "&($B$6-1)&" compatible")) -> 29% — 14 of 49 compatible
... A120: =IFERROR(INDEX('Matching Engine'!A$2:A$201,MATCH(ROW()-71,'Matching Engine'!M$2:M$201,0)),"") -> Terezi Pyrope | B120: =IF(A120="","",INDEX('Matching Engine'!B$2:B$201,MATCH(A120,'Matching Engine'!A$2:A$201,0))) -> Female | C120: =IF(A120="","",IF(AND(INDEX('Matching Engine'!F$2:F$201,MATCH(A120,'Matching Engine'!A$2:A$201,0))=0,INDEX('Matching Engine'!G$2:G$201,MATCH(A120,'Matching Engine'!A$2:A$201,0))=0,INDEX('Matching Engine'!H$2:H$201,MATCH(A120,'Matching Engine'!A$2:A$201,0))=0),"None",IF(INDEX('Matching Engine'!F$2:F$201,MATCH(A120,'Matching Engine'!A$2:A$201,0))=1,"♂ ","")&IF(INDEX('Matching Engine'!G$2:G$201,MATCH(A120,'Matching Engine'!A$2:A$201,0))=1,"♀ ","")&IF(INDEX('Matching Engine'!H$2:H$201,MATCH(A120,'Matching Engine'!A$2:A$201,0))=1,"⚧",""))) -> ♂ ♀ ⚧ | D120: =IF(A120="","",INDEX('Matching Engine'!L$2:L$201,MATCH(A120,'Matching Engine'!A$2:A$201,0))) -> 38 | E120: =IF(A120="","",IF(D120=0,"0% — no compatible partners",TEXT(D120/($B$6-1),"0%")&" — "&D120&" of "&($B$6-1)&" compatible")) -> 78% — 38 of 49 compatible
A121: =IFERROR(INDEX('Matching Engine'!A$2:A$201,MATCH(ROW()-68,'Matching Engine'!M$2:M$201,0)),"") | B121: =IF(A121="","",INDEX('Matching Engine'!B$2:B$201,MATCH(A121,'Matching Engine'!A$2:A$201,0))) | C121: =IF(A121="","",IF(AND(INDEX('Matching Engine'!F$2:F$201,MATCH(A121,'Matching Engine'!A$2:A$201,0))=0,INDEX('Matching Engine'!G$2:G$201,MATCH(A121,'Matching Engine'!A$2:A$201,0))=0,INDEX('Matching Engine'!H$2:H$201,MATCH(A121,'Matching Engine'!A$2:A$201,0))=0),"None",IF(INDEX('Matching Engine'!F$2:F$201,MATCH(A121,'Matching Engine'!A$2:A$201,0))=1,"♂ ","")&IF(INDEX('Matching Engine'!G$2:G$201,MATCH(A121,'Matching Engine'!A$2:A$201,0))=1,"♀ ","")&IF(INDEX('Matching Engine'!H$2:H$201,MATCH(A121,'Matching Engine'!A$2:A$201,0))=1,"⚧",""))) | D121: =IF(A121="","",INDEX('Matching Engine'!L$2:L$201,MATCH(A121,'Matching Engine'!A$2:A$201,0))) | E121: =IF(A121="","",IF(D121=0,"0% — no compatible partners",TEXT(D121/($B$6-1),"0%")&" — "&D121&" of "&($B$6-1)&" compatible"))
A122: =IFERROR(INDEX('Matching Engine'!A$2:A$201,MATCH(ROW()-68,'Matching Engine'!M$2:M$201,0)),"") | B122: =IF(A122="","",INDEX('Matching Engine'!B$2:B$201,MATCH(A122,'Matching Engine'!A$2:A$201,0))) | C122: =IF(A122="","",IF(AND(INDEX('Matching Engine'!F$2:F$201,MATCH(A122,'Matching Engine'!A$2:A$201,0))=0,INDEX('Matching Engine'!G$2:G$201,MATCH(A122,'Matching Engine'!A$2:A$201,0))=0,INDEX('Matching Engine'!H$2:H$201,MATCH(A122,'Matching Engine'!A$2:A$201,0))=0),"None",IF(INDEX('Matching Engine'!F$2:F$201,MATCH(A122,'Matching Engine'!A$2:A$201,0))=1,"♂ ","")&IF(INDEX('Matching Engine'!G$2:G$201,MATCH(A122,'Matching Engine'!A$2:A$201,0))=1,"♀ ","")&IF(INDEX('Matching Engine'!H$2:H$201,MATCH(A122,'Matching Engine'!A$2:A$201,0))=1,"⚧",""))) | D122: =IF(A122="","",INDEX('Matching Engine'!L$2:L$201,MATCH(A122,'Matching Engine'!A$2:A$201,0))) | E122: =IF(A122="","",IF(D122=0,"0% — no compatible partners",TEXT(D122/($B$6-1),"0%")&" — "&D122&" of "&($B$6-1)&" compatible"))
A123: =IFERROR(INDEX('Matching Engine'!A$2:A$201,MATCH(ROW()-68,'Matching Engine'!M$2:M$201,0)),"") | B123: =IF(A123="","",INDEX('Matching Engine'!B$2:B$201,MATCH(A123,'Matching Engine'!A$2:A$201,0))) | C123: =IF(A123="","",IF(AND(INDEX('Matching Engine'!F$2:F$201,MATCH(A123,'Matching Engine'!A$2:A$201,0))=0,INDEX('Matching Engine'!G$2:G$201,MATCH(A123,'Matching Engine'!A$2:A$201,0))=0,INDEX('Matching Engine'!H$2:H$201,MATCH(A123,'Matching Engine'!A$2:A$201,0))=0),"None",IF(INDEX('Matching Engine'!F$2:F$201,MATCH(A123,'Matching Engine'!A$2:A$201,0))=1,"♂ ","")&IF(INDEX('Matching Engine'!G$2:G$201,MATCH(A123,'Matching Engine'!A$2:A$201,0))=1,"♀ ","")&IF(INDEX('Matching Engine'!H$2:H$201,MATCH(A123,'Matching Engine'!A$2:A$201,0))=1,"⚧",""))) | D123: =IF(A123="","",INDEX('Matching Engine'!L$2:L$201,MATCH(A123,'Matching Engine'!A$2:A$201,0))) | E123: =IF(A123="","",IF(D123=0,"0% — no compatible partners",TEXT(D123/($B$6-1),"0%")&" — "&D123&" of "&($B$6-1)&" compatible"))
A124: =IFERROR(INDEX('Matching Engine'!A$2:A$201,MATCH(ROW()-68,'Matching Engine'!M$2:M$201,0)),"") | B124: =IF(A124="","",INDEX('Matching Engine'!B$2:B$201,MATCH(A124,'Matching Engine'!A$2:A$201,0))) | C124: =IF(A124="","",IF(AND(INDEX('Matching Engine'!F$2:F$201,MATCH(A124,'Matching Engine'!A$2:A$201,0))=0,INDEX('Matching Engine'!G$2:G$201,MATCH(A124,'Matching Engine'!A$2:A$201,0))=0,INDEX('Matching Engine'!H$2:H$201,MATCH(A124,'Matching Engine'!A$2:A$201,0))=0),"None",IF(INDEX('Matching Engine'!F$2:F$201,MATCH(A124,'Matching Engine'!A$2:A$201,0))=1,"♂ ","")&IF(INDEX('Matching Engine'!G$2:G$201,MATCH(A124,'Matching Engine'!A$2:A$201,0))=1,"♀ ","")&IF(INDEX('Matching Engine'!H$2:H$201,MATCH(A124,'Matching Engine'!A$2:A$201,0))=1,"⚧",""))) | D124: =IF(A124="","",INDEX('Matching Engine'!L$2:L$201,MATCH(A124,'Matching Engine'!A$2:A$201,0))) | E124: =IF(A124="","",IF(D124=0,"0% — no compatible partners",TEXT(D124/($B$6-1),"0%")&" — "&D124&" of "&($B$6-1)&" compatible"))
A125: =IFERROR(INDEX('Matching Engine'!A$2:A$201,MATCH(ROW()-68,'Matching Engine'!M$2:M$201,0)),"") | B125: =IF(A125="","",INDEX('Matching Engine'!B$2:B$201,MATCH(A125,'Matching Engine'!A$2:A$201,0))) | C125: =IF(A125="","",IF(AND(INDEX('Matching Engine'!F$2:F$201,MATCH(A125,'Matching Engine'!A$2:A$201,0))=0,INDEX('Matching Engine'!G$2:G$201,MATCH(A125,'Matching Engine'!A$2:A$201,0))=0,INDEX('Matching Engine'!H$2:H$201,MATCH(A125,'Matching Engine'!A$2:A$201,0))=0),"None",IF(INDEX('Matching Engine'!F$2:F$201,MATCH(A125,'Matching Engine'!A$2:A$201,0))=1,"♂ ","")&IF(INDEX('Matching Engine'!G$2:G$201,MATCH(A125,'Matching Engine'!A$2:A$201,0))=1,"♀ ","")&IF(INDEX('Matching Engine'!H$2:H$201,MATCH(A125,'Matching Engine'!A$2:A$201,0))=1,"⚧",""))) | D125: =IF(A125="","",INDEX('Matching Engine'!L$2:L$201,MATCH(A125,'Matching Engine'!A$2:A$201,0))) | E125: =IF(A125="","",IF(D125=0,"0% — no compatible partners",TEXT(D125/($B$6-1),"0%")&" — "&D125&" of "&($B$6-1)&" compatible"))
A126: =IFERROR(INDEX('Matching Engine'!A$2:A$201,MATCH(ROW()-68,'Matching Engine'!M$2:M$201,0)),"") | B126: =IF(A126="","",INDEX('Matching Engine'!B$2:B$201,MATCH(A126,'Matching Engine'!A$2:A$201,0))) | C126: =IF(A126="","",IF(AND(INDEX('Matching Engine'!F$2:F$201,MATCH(A126,'Matching Engine'!A$2:A$201,0))=0,INDEX('Matching Engine'!G$2:G$201,MATCH(A126,'Matching Engine'!A$2:A$201,0))=0,INDEX('Matching Engine'!H$2:H$201,MATCH(A126,'Matching Engine'!A$2:A$201,0))=0),"None",IF(INDEX('Matching Engine'!F$2:F$201,MATCH(A126,'Matching Engine'!A$2:A$201,0))=1,"♂ ","")&IF(INDEX('Matching Engine'!G$2:G$201,MATCH(A126,'Matching Engine'!A$2:A$201,0))=1,"♀ ","")&IF(INDEX('Matching Engine'!H$2:H$201,MATCH(A126,'Matching Engine'!A$2:A$201,0))=1,"⚧",""))) | D126: =IF(A126="","",INDEX('Matching Engine'!L$2:L$201,MATCH(A126,'Matching Engine'!A$2:A$201,0))) | E126: =IF(A126="","",IF(D126=0,"0% — no compatible partners",TEXT(D126/($B$6-1),"0%")&" — "&D126&" of "&($B$6-1)&" compatible"))
A127: =IFERROR(INDEX('Matching Engine'!A$2:A$201,MATCH(ROW()-68,'Matching Engine'!M$2:M$201,0)),"") | B127: =IF(A127="","",INDEX('Matching Engine'!B$2:B$201,MATCH(A127,'Matching Engine'!A$2:A$201,0))) | C127: =IF(A127="","",IF(AND(INDEX('Matching Engine'!F$2:F$201,MATCH(A127,'Matching Engine'!A$2:A$201,0))=0,INDEX('Matching Engine'!G$2:G$201,MATCH(A127,'Matching Engine'!A$2:A$201,0))=0,INDEX('Matching Engine'!H$2:H$201,MATCH(A127,'Matching Engine'!A$2:A$201,0))=0),"None",IF(INDEX('Matching Engine'!F$2:F$201,MATCH(A127,'Matching Engine'!A$2:A$201,0))=1,"♂ ","")&IF(INDEX('Matching Engine'!G$2:G$201,MATCH(A127,'Matching Engine'!A$2:A$201,0))=1,"♀ ","")&IF(INDEX('Matching Engine'!H$2:H$201,MATCH(A127,'Matching Engine'!A$2:A$201,0))=1,"⚧",""))) | D127: =IF(A127="","",INDEX('Matching Engine'!L$2:L$201,MATCH(A127,'Matching Engine'!A$2:A$201,0))) | E127: =IF(A127="","",IF(D127=0,"0% — no compatible partners",TEXT(D127/($B$6-1),"0%")&" — "&D127&" of "&($B$6-1)&" compatible"))
A128: =IFERROR(INDEX('Matching Engine'!A$2:A$201,MATCH(ROW()-68,'Matching Engine'!M$2:M$201,0)),"") | B128: =IF(A128="","",INDEX('Matching Engine'!B$2:B$201,MATCH(A128,'Matching Engine'!A$2:A$201,0))) | C128: =IF(A128="","",IF(AND(INDEX('Matching Engine'!F$2:F$201,MATCH(A128,'Matching Engine'!A$2:A$201,0))=0,INDEX('Matching Engine'!G$2:G$201,MATCH(A128,'Matching Engine'!A$2:A$201,0))=0,INDEX('Matching Engine'!H$2:H$201,MATCH(A128,'Matching Engine'!A$2:A$201,0))=0),"None",IF(INDEX('Matching Engine'!F$2:F$201,MATCH(A128,'Matching Engine'!A$2:A$201,0))=1,"♂ ","")&IF(INDEX('Matching Engine'!G$2:G$201,MATCH(A128,'Matching Engine'!A$2:A$201,0))=1,"♀ ","")&IF(INDEX('Matching Engine'!H$2:H$201,MATCH(A128,'Matching Engine'!A$2:A$201,0))=1,"⚧",""))) | D128: =IF(A128="","",INDEX('Matching Engine'!L$2:L$201,MATCH(A128,'Matching Engine'!A$2:A$201,0))) | E128: =IF(A128="","",IF(D128=0,"0% — no compatible partners",TEXT(D128/($B$6-1),"0%")&" — "&D128&" of "&($B$6-1)&" compatible"))
A129: =IFERROR(INDEX('Matching Engine'!A$2:A$201,MATCH(ROW()-68,'Matching Engine'!M$2:M$201,0)),"") | B129: =IF(A129="","",INDEX('Matching Engine'!B$2:B$201,MATCH(A129,'Matching Engine'!A$2:A$201,0))) | C129: =IF(A129="","",IF(AND(INDEX('Matching Engine'!F$2:F$201,MATCH(A129,'Matching Engine'!A$2:A$201,0))=0,INDEX('Matching Engine'!G$2:G$201,MATCH(A129,'Matching Engine'!A$2:A$201,0))=0,INDEX('Matching Engine'!H$2:H$201,MATCH(A129,'Matching Engine'!A$2:A$201,0))=0),"None",IF(INDEX('Matching Engine'!F$2:F$201,MATCH(A129,'Matching Engine'!A$2:A$201,0))=1,"♂ ","")&IF(INDEX('Matching Engine'!G$2:G$201,MATCH(A129,'Matching Engine'!A$2:A$201,0))=1,"♀ ","")&IF(INDEX('Matching Engine'!H$2:H$201,MATCH(A129,'Matching Engine'!A$2:A$201,0))=1,"⚧",""))) | D129: =IF(A129="","",INDEX('Matching Engine'!L$2:L$201,MATCH(A129,'Matching Engine'!A$2:A$201,0))) | E129: =IF(A129="","",IF(D129=0,"0% — no compatible partners",TEXT(D129/($B$6-1),"0%")&" — "&D129&" of "&($B$6-1)&" compatible"))
A130: =IFERROR(INDEX('Matching Engine'!A$2:A$201,MATCH(ROW()-68,'Matching Engine'!M$2:M$201,0)),"") | B130: =IF(A130="","",INDEX('Matching Engine'!B$2:B$201,MATCH(A130,'Matching Engine'!A$2:A$201,0))) | C130: =IF(A130="","",IF(AND(INDEX('Matching Engine'!F$2:F$201,MATCH(A130,'Matching Engine'!A$2:A$201,0))=0,INDEX('Matching Engine'!G$2:G$201,MATCH(A130,'Matching Engine'!A$2:A$201,0))=0,INDEX('Matching Engine'!H$2:H$201,MATCH(A130,'Matching Engine'!A$2:A$201,0))=0),"None",IF(INDEX('Matching Engine'!F$2:F$201,MATCH(A130,'Matching Engine'!A$2:A$201,0))=1,"♂ ","")&IF(INDEX('Matching Engine'!G$2:G$201,MATCH(A130,'Matching Engine'!A$2:A$201,0))=1,"♀ ","")&IF(INDEX('Matching Engine'!H$2:H$201,MATCH(A130,'Matching Engine'!A$2:A$201,0))=1,"⚧",""))) | D130: =IF(A130="","",INDEX('Matching Engine'!L$2:L$201,MATCH(A130,'Matching Engine'!A$2:A$201,0))) | E130: =IF(A130="","",IF(D130=0,"0% — no compatible partners",TEXT(D130/($B$6-1),"0%")&" — "&D130&" of "&($B$6-1)&" compatible"))
A131: =IFERROR(INDEX('Matching Engine'!A$2:A$201,MATCH(ROW()-68,'Matching Engine'!M$2:M$201,0)),"") | B131: =IF(A131="","",INDEX('Matching Engine'!B$2:B$201,MATCH(A131,'Matching Engine'!A$2:A$201,0))) | C131: =IF(A131="","",IF(AND(INDEX('Matching Engine'!F$2:F$201,MATCH(A131,'Matching Engine'!A$2:A$201,0))=0,INDEX('Matching Engine'!G$2:G$201,MATCH(A131,'Matching Engine'!A$2:A$201,0))=0,INDEX('Matching Engine'!H$2:H$201,MATCH(A131,'Matching Engine'!A$2:A$201,0))=0),"None",IF(INDEX('Matching Engine'!F$2:F$201,MATCH(A131,'Matching Engine'!A$2:A$201,0))=1,"♂ ","")&IF(INDEX('Matching Engine'!G$2:G$201,MATCH(A131,'Matching Engine'!A$2:A$201,0))=1,"♀ ","")&IF(INDEX('Matching Engine'!H$2:H$201,MATCH(A131,'Matching Engine'!A$2:A$201,0))=1,"⚧",""))) | D131: =IF(A131="","",INDEX('Matching Engine'!L$2:L$201,MATCH(A131,'Matching Engine'!A$2:A$201,0))) | E131: =IF(A131="","",IF(D131=0,"0% — no compatible partners",TEXT(D131/($B$6-1),"0%")&" — "&D131&" of "&($B$6-1)&" compatible"))
A132: =IFERROR(INDEX('Matching Engine'!A$2:A$201,MATCH(ROW()-68,'Matching Engine'!M$2:M$201,0)),"") | B132: =IF(A132="","",INDEX('Matching Engine'!B$2:B$201,MATCH(A132,'Matching Engine'!A$2:A$201,0))) | C132: =IF(A132="","",IF(AND(INDEX('Matching Engine'!F$2:F$201,MATCH(A132,'Matching Engine'!A$2:A$201,0))=0,INDEX('Matching Engine'!G$2:G$201,MATCH(A132,'Matching Engine'!A$2:A$201,0))=0,INDEX('Matching Engine'!H$2:H$201,MATCH(A132,'Matching Engine'!A$2:A$201,0))=0),"None",IF(INDEX('Matching Engine'!F$2:F$201,MATCH(A132,'Matching Engine'!A$2:A$201,0))=1,"♂ ","")&IF(INDEX('Matching Engine'!G$2:G$201,MATCH(A132,'Matching Engine'!A$2:A$201,0))=1,"♀ ","")&IF(INDEX('Matching Engine'!H$2:H$201,MATCH(A132,'Matching Engine'!A$2:A$201,0))=1,"⚧",""))) | D132: =IF(A132="","",INDEX('Matching Engine'!L$2:L$201,MATCH(A132,'Matching Engine'!A$2:A$201,0))) | E132: =IF(A132="","",IF(D132=0,"0% — no compatible partners",TEXT(D132/($B$6-1),"0%")&" — "&D132&" of "&($B$6-1)&" compatible"))
... A174: =IFERROR(INDEX('Matching Engine'!A$2:A$201,MATCH(ROW()-68,'Matching Engine'!M$2:M$201,0)),"") | B174: =IF(A174="","",INDEX('Matching Engine'!B$2:B$201,MATCH(A174,'Matching Engine'!A$2:A$201,0))) | C174: =IF(A174="","",IF(AND(INDEX('Matching Engine'!F$2:F$201,MATCH(A174,'Matching Engine'!A$2:A$201,0))=0,INDEX('Matching Engine'!G$2:G$201,MATCH(A174,'Matching Engine'!A$2:A$201,0))=0,INDEX('Matching Engine'!H$2:H$201,MATCH(A174,'Matching Engine'!A$2:A$201,0))=0),"None",IF(INDEX('Matching Engine'!F$2:F$201,MATCH(A174,'Matching Engine'!A$2:A$201,0))=1,"♂ ","")&IF(INDEX('Matching Engine'!G$2:G$201,MATCH(A174,'Matching Engine'!A$2:A$201,0))=1,"♀ ","")&IF(INDEX('Matching Engine'!H$2:H$201,MATCH(A174,'Matching Engine'!A$2:A$201,0))=1,"⚧",""))) | D174: =IF(A174="","",INDEX('Matching Engine'!L$2:L$201,MATCH(A174,'Matching Engine'!A$2:A$201,0))) | E174: =IF(A174="","",IF(D174=0,"0% — no compatible partners",TEXT(D174/($B$6-1),"0%")&" — "&D174&" of "&($B$6-1)&" compatible"))

Sheet Matching Engine
A1: Name | B1: Gender | C1: ♂? | D1: ♀? | E1: ⚧? | F1: Wants M | G1: Wants F | H1: Wants NB | I1: Is M | J1: Is F | K1: Is NB | L1: # Compatible | M1: Rank | N1: Demand Rate (H) | O1: Avg Partner Compat | P1: CR Scale
A2: {=IF(ROW()-1>COUNTA('Mii List'!A$2:A$200),"",INDEX('Mii List'!A$2:A$200,ROW()-1))} -> Robin | B2: =IF(A2="","",INDEX('Mii List'!B$2:B$200,MATCH(A2,'Mii List'!A$2:A$200,0))) -> Nonbinary | C2: =IF(A2="","",INDEX('Mii List'!C$2:C$200,MATCH(A2,'Mii List'!A$2:A$200,0))) -> ✓ | D2: =IF(A2="","",INDEX('Mii List'!D$2:D$200,MATCH(A2,'Mii List'!A$2:A$200,0))) -> ✓ | E2: =IF(A2="","",INDEX('Mii List'!E$2:E$200,MATCH(A2,'Mii List'!A$2:A$200,0))) -> ✓ | F2: =IF(A2="",0,(C2="✓")*1) -> 1 | G2: =IF(A2="",0,(D2="✓")*1) -> 1 | H2: =IF(A2="",0,(E2="✓")*1) -> 1 | I2: =IF(A2="",0,(B2="Male")*1) -> 0 | J2: =IF(A2="",0,(B2="Female")*1) -> 0 | K2: =IF(A2="",0,(B2="Nonbinary")*1) -> 1 | L2: {=IF(A2="",0,SUMPRODUCT((A$2:A$201<>"")*((F$2:F$201*I2+G$2:G$201*J2+H$2:H$201*K2)>0)*((F2*I$2:I$201+G2*J$2:J$201+H2*K$2:K$201)>0))-IF(F2*I2+G2*J2+H2*K2>0,1,0))} -> 23 | M2: {=IF(A2="","",SUMPRODUCT((A$2:A$201<>"")*(L$2:L$201<L2))+SUMPRODUCT((A$2:A$201<>"")*(L$2:L$201=L2)*(A$2:A$201<A2))+1)} -> 24 | N2: {=IF(A2="","",SUMPRODUCT(((OFFSET(F$2,0,0,COUNTA('Mii List'!A$2:A$200),1)*I2+OFFSET(G$2,0,0,COUNTA('Mii List'!A$2:A$200),1)*J2+OFFSET(H$2,0,0,COUNTA('Mii List'!A$2:A$200),1)*K2)>0)*((F2*OFFSET(I$2,0,0,COUNTA('Mii List'!A$2:A$200),1)+G2*OFFSET(J$2,0,0,COUNTA('Mii List'!A$2:A$200),1)+H2*OFFSET(K$2,0,0,COUNTA('Mii List'!A$2:A$200),1))>0)*(ROW(OFFSET($A$2,0,0,COUNTA('Mii List'!A$2:A$200),1))<>ROW())*IF(OFFSET(L$2,0,0,COUNTA('Mii List'!A$2:A$200),1)>0,1/OFFSET(L$2,0,0,COUNTA('Mii List'!A$2:A$200),1),0)))} -> 0.73406433 | O2: {=IF(A2="","",IF(L2=0,0,SUMPRODUCT(((OFFSET(F$2,0,0,COUNTA('Mii List'!A$2:A$200),1)*I2+OFFSET(G$2,0,0,COUNTA('Mii List'!A$2:A$200),1)*J2+OFFSET(H$2,0,0,COUNTA('Mii List'!A$2:A$200),1)*K2)>0)*((F2*OFFSET(I$2,0,0,COUNTA('Mii List'!A$2:A$200),1)+G2*OFFSET(J$2,0,0,COUNTA('Mii List'!A$2:A$200),1)+H2*OFFSET(K$2,0,0,COUNTA('Mii List'!A$2:A$200),1))>0)*(ROW(OFFSET($A$2,0,0,COUNTA('Mii List'!A$2:A$200),1))<>ROW())*OFFSET(L$2,0,0,COUNTA('Mii List'!A$2:A$200),1))/L2))} -> 33 | P2: =IF(A2="","",IF(L2*O2>0,MIN(1,L2/O2),0)) -> 0.6969697
A3: {=IF(ROW()-1>COUNTA('Mii List'!A$2:A$200),"",INDEX('Mii List'!A$2:A$200,ROW()-1))} -> Nny | B3: =IF(A3="","",INDEX('Mii List'!B$2:B$200,MATCH(A3,'Mii List'!A$2:A$200,0))) -> Nonbinary | C3: =IF(A3="","",INDEX('Mii List'!C$2:C$200,MATCH(A3,'Mii List'!A$2:A$200,0))) -> ✗ | D3: =IF(A3="","",INDEX('Mii List'!D$2:D$200,MATCH(A3,'Mii List'!A$2:A$200,0))) -> ✗ | E3: =IF(A3="","",INDEX('Mii List'!E$2:E$200,MATCH(A3,'Mii List'!A$2:A$200,0))) -> ✗ | F3: =IF(A3="",0,(C3="✓")*1) -> 0 | G3: =IF(A3="",0,(D3="✓")*1) -> 0 | H3: =IF(A3="",0,(E3="✓")*1) -> 0 | I3: =IF(A3="",0,(B3="Male")*1) -> 0 | J3: =IF(A3="",0,(B3="Female")*1) -> 0 | K3: =IF(A3="",0,(B3="Nonbinary")*1) -> 1 | L3: {=IF(A3="",0,SUMPRODUCT((A$2:A$201<>"")*((F$2:F$201*I3+G$2:G$201*J3+H$2:H$201*K3)>0)*((F3*I$2:I$201+G3*J$2:J$201+H3*K$2:K$201)>0))-IF(F3*I3+G3*J3+H3*K3>0,1,0))} -> 0 | M3: {=IF(A3="","",SUMPRODUCT((A$2:A$201<>"")*(L$2:L$201<L3))+SUMPRODUCT((A$2:A$201<>"")*(L$2:L$201=L3)*(A$2:A$201<A3))+1)} -> 1 | N3: {=IF(A3="","",SUMPRODUCT(((OFFSET(F$2,0,0,COUNTA('Mii List'!A$2:A$200),1)*I3+OFFSET(G$2,0,0,COUNTA('Mii List'!A$2:A$200),1)*J3+OFFSET(H$2,0,0,COUNTA('Mii List'!A$2:A$200),1)*K3)>0)*((F3*OFFSET(I$2,0,0,COUNTA('Mii List'!A$2:A$200),1)+G3*OFFSET(J$2,0,0,COUNTA('Mii List'!A$2:A$200),1)+H3*OFFSET(K$2,0,0,COUNTA('Mii List'!A$2:A$200),1))>0)*(ROW(OFFSET($A$2,0,0,COUNTA('Mii List'!A$2:A$200),1))<>ROW())*IF(OFFSET(L$2,0,0,COUNTA('Mii List'!A$2:A$200),1)>0,1/OFFSET(L$2,0,0,COUNTA('Mii List'!A$2:A$200),1),0)))} -> 0 | O3: {=IF(A3="","",IF(L3=0,0,SUMPRODUCT(((OFFSET(F$2,0,0,COUNTA('Mii List'!A$2:A$200),1)*I3+OFFSET(G$2,0,0,COUNTA('Mii List'!A$2:A$200),1)*J3+OFFSET(H$2,0,0,COUNTA('Mii List'!A$2:A$200),1)*K3)>0)*((F3*OFFSET(I$2,0,0,COUNTA('Mii List'!A$2:A$200),1)+G3*OFFSET(J$2,0,0,COUNTA('Mii List'!A$2:A$200),1)+H3*OFFSET(K$2,0,0,COUNTA('Mii List'!A$2:A$200),1))>0)*(ROW(OFFSET($A$2,0,0,COUNTA('Mii List'!A$2:A$200),1))<>ROW())*OFFSET(L$2,0,0,COUNTA('Mii List'!A$2:A$200),1))/L3))} -> 0 | P3: =IF(A3="","",IF(L3*O3>0,MIN(1,L3/O3),0)) -> 0
A4: {=IF(ROW()-1>COUNTA('Mii List'!A$2:A$200),"",INDEX('Mii List'!A$2:A$200,ROW()-1))} -> Barack Obama | B4: =IF(A4="","",INDEX('Mii List'!B$2:B$200,MATCH(A4,'Mii List'!A$2:A$200,0))) -> Male | C4: =IF(A4="","",INDEX('Mii List'!C$2:C$200,MATCH(A4,'Mii List'!A$2:A$200,0))) -> ✗ | D4: =IF(A4="","",INDEX('Mii List'!D$2:D$200,MATCH(A4,'Mii List'!A$2:A$200,0))) -> ✓ | E4: =IF(A4="","",INDEX('Mii List'!E$2:E$200,MATCH(A4,'Mii List'!A$2:A$200,0))) -> ✗ | F4: =IF(A4="",0,(C4="✓")*1) -> 0 | G4: =IF(A4="",0,(D4="✓")*1) -> 1 | H4: =IF(A4="",0,(E4="✓")*1) -> 0 | I4: =IF(A4="",0,(B4="Male")*1) -> 1 | J4: =IF(A4="",0,(B4="Female")*1) -> 0 | K4: =IF(A4="",0,(B4="Nonbinary")*1) -> 0 | L4: {=IF(A4="",0,SUMPRODUCT((A$2:A$201<>"")*((F$2:F$201*I4+G$2:G$201*J4+H$2:H$201*K4)>0)*((F4*I$2:I$201+G4*J$2:J$201+H4*K$2:K$201)>0))-IF(F4*I4+G4*J4+H4*K4>0,1,0))} -> 14 | M4: {=IF(A4="","",SUMPRODUCT((A$2:A$201<>"")*(L$2:L$201<L4))+SUMPRODUCT((A$2:A$201<>"")*(L$2:L$201=L4)*(A$2:A$201<A4))+1)} -> 4 | N4: {=IF(A4="","",SUMPRODUCT(((OFFSET(F$2,0,0,COUNTA('Mii List'!A$2:A$200),1)*I4+OFFSET(G$2,0,0,COUNTA('Mii List'!A$2:A$200),1)*J4+OFFSET(H$2,0,0,COUNTA('Mii List'!A$2:A$200),1)*K4)>0)*((F4*OFFSET(I$2,0,0,COUNTA('Mii List'!A$2:A$200),1)+G4*OFFSET(J$2,0,0,COUNTA('Mii List'!A$2:A$200),1)+H4*OFFSET(K$2,0,0,COUNTA('Mii List'!A$2:A$200),1))>0)*(ROW(OFFSET($A$2,0,0,COUNTA('Mii List'!A$2:A$200),1))<>ROW())*IF(OFFSET(L$2,0,0,COUNTA('Mii List'!A$2:A$200),1)>0,1/OFFSET(L$2,0,0,COUNTA('Mii List'!A$2:A$200),1),0)))} -> 0.41771529 | O4: {=IF(A4="","",IF(L4=0,0,SUMPRODUCT(((OFFSET(F$2,0,0,COUNTA('Mii List'!A$2:A$200),1)*I4+OFFSET(G$2,0,0,COUNTA('Mii List'!A$2:A$200),1)*J4+OFFSET(H$2,0,0,COUNTA('Mii List'!A$2:A$200),1)*K4)>0)*((F4*OFFSET(I$2,0,0,COUNTA('Mii List'!A$2:A$200),1)+G4*OFFSET(J$2,0,0,COUNTA('Mii List'!A$2:A$200),1)+H4*OFFSET(K$2,0,0,COUNTA('Mii List'!A$2:A$200),1))>0)*(ROW(OFFSET($A$2,0,0,COUNTA('Mii List'!A$2:A$200),1))<>ROW())*OFFSET(L$2,0,0,COUNTA('Mii List'!A$2:A$200),1))/L4))} -> 34.5 | P4: =IF(A4="","",IF(L4*O4>0,MIN(1,L4/O4),0)) -> 0.4057971
A5: {=IF(ROW()-1>COUNTA('Mii List'!A$2:A$200),"",INDEX('Mii List'!A$2:A$200,ROW()-1))} -> Randy Sexton | B5: =IF(A5="","",INDEX('Mii List'!B$2:B$200,MATCH(A5,'Mii List'!A$2:A$200,0))) -> Male | C5: =IF(A5="","",INDEX('Mii List'!C$2:C$200,MATCH(A5,'Mii List'!A$2:A$200,0))) -> ✓ | D5: =IF(A5="","",INDEX('Mii List'!D$2:D$200,MATCH(A5,'Mii List'!A$2:A$200,0))) -> ✓ | E5: =IF(A5="","",INDEX('Mii List'!E$2:E$200,MATCH(A5,'Mii List'!A$2:A$200,0))) -> ✓ | F5: =IF(A5="",0,(C5="✓")*1) -> 1 | G5: =IF(A5="",0,(D5="✓")*1) -> 1 | H5: =IF(A5="",0,(E5="✓")*1) -> 1 | I5: =IF(A5="",0,(B5="Male")*1) -> 1 | J5: =IF(A5="",0,(B5="Female")*1) -> 0 | K5: =IF(A5="",0,(B5="Nonbinary")*1) -> 0 | L5: {=IF(A5="",0,SUMPRODUCT((A$2:A$201<>"")*((F$2:F$201*I5+G$2:G$201*J5+H$2:H$201*K5)>0)*((F5*I$2:I$201+G5*J$2:J$201+H5*K$2:K$201)>0))-IF(F5*I5+G5*J5+H5*K5>0,1,0))} -> 32 | M5: {=IF(A5="","",SUMPRODUCT((A$2:A$201<>"")*(L$2:L$201<L5))+SUMPRODUCT((A$2:A$201<>"")*(L$2:L$201=L5)*(A$2:A$201<A5))+1)} -> 38 | N5: {=IF(A5="","",SUMPRODUCT(((OFFSET(F$2,0,0,COUNTA('Mii List'!A$2:A$200),1)*I5+OFFSET(G$2,0,0,COUNTA('Mii List'!A$2:A$200),1)*J5+OFFSET(H$2,0,0,COUNTA('Mii List'!A$2:A$200),1)*K5)>0)*((F5*OFFSET(I$2,0,0,COUNTA('Mii List'!A$2:A$200),1)+G5*OFFSET(J$2,0,0,COUNTA('Mii List'!A$2:A$200),1)+H5*OFFSET(K$2,0,0,COUNTA('Mii List'!A$2:A$200),1))>0)*(ROW(OFFSET($A$2,0,0,COUNTA('Mii List'!A$2:A$200),1))<>ROW())*IF(OFFSET(L$2,0,0,COUNTA('Mii List'!A$2:A$200),1)>0,1/OFFSET(L$2,0,0,COUNTA('Mii List'!A$2:A$200),1),0)))} -> 1.1546167 | O5: {=IF(A5="","",IF(L5=0,0,SUMPRODUCT(((OFFSET(F$2,0,0,COUNTA('Mii List'!A$2:A$200),1)*I5+OFFSET(G$2,0,0,COUNTA('Mii List'!A$2:A$200),1)*J5+OFFSET(H$2,0,0,COUNTA('Mii List'!A$2:A$200),1)*K5)>0)*((F5*OFFSET(I$2,0,0,COUNTA('Mii List'!A$2:A$200),1)+G5*OFFSET(J$2,0,0,COUNTA('Mii List'!A$2:A$200),1)+H5*OFFSET(K$2,0,0,COUNTA('Mii List'!A$2:A$200),1))>0)*(ROW(OFFSET($A$2,0,0,COUNTA('Mii List'!A$2:A$200),1))<>ROW())*OFFSET(L$2,0,0,COUNTA('Mii List'!A$2:A$200),1))/L5))} -> 30.03125 | P5: =IF(A5="","",IF(L5*O5>0,MIN(1,L5/O5),0)) -> 1
A6: {=IF(ROW()-1>COUNTA('Mii List'!A$2:A$200),"",INDEX('Mii List'!A$2:A$200,ROW()-1))} -> Biff Williams | B6: =IF(A6="","",INDEX('Mii List'!B$2:B$200,MATCH(A6,'Mii List'!A$2:A$200,0))) -> Male | C6: =IF(A6="","",INDEX('Mii List'!C$2:C$200,MATCH(A6,'Mii List'!A$2:A$200,0))) -> ✗ | D6: =IF(A6="","",INDEX('Mii List'!D$2:D$200,MATCH(A6,'Mii List'!A$2:A$200,0))) -> ✓ | E6: =IF(A6="","",INDEX('Mii List'!E$2:E$200,MATCH(A6,'Mii List'!A$2:A$200,0))) -> ✗ | F6: =IF(A6="",0,(C6="✓")*1) -> 0 | G6: =IF(A6="",0,(D6="✓")*1) -> 1 | H6: =IF(A6="",0,(E6="✓")*1) -> 0 | I6: =IF(A6="",0,(B6="Male")*1) -> 1 | J6: =IF(A6="",0,(B6="Female")*1) -> 0 | K6: =IF(A6="",0,(B6="Nonbinary")*1) -> 0 | L6: {=IF(A6="",0,SUMPRODUCT((A$2:A$201<>"")*((F$2:F$201*I6+G$2:G$201*J6+H$2:H$201*K6)>0)*((F6*I$2:I$201+G6*J$2:J$201+H6*K$2:K$201)>0))-IF(F6*I6+G6*J6+H6*K6>0,1,0))} -> 14 | M6: {=IF(A6="","",SUMPRODUCT((A$2:A$201<>"")*(L$2:L$201<L6))+SUMPRODUCT((A$2:A$201<>"")*(L$2:L$201=L6)*(A$2:A$201<A6))+1)} -> 6 | N6: {=IF(A6="","",SUMPRODUCT(((OFFSET(F$2,0,0,COUNTA('Mii List'!A$2:A$200),1)*I6+OFFSET(G$2,0,0,COUNTA('Mii List'!A$2:A$200),1)*J6+OFFSET(H$2,0,0,COUNTA('Mii List'!A$2:A$200),1)*K6)>0)*((F6*OFFSET(I$2,0,0,COUNTA('Mii List'!A$2:A$200),1)+G6*OFFSET(J$2,0,0,COUNTA('Mii List'!A$2:A$200),1)+H6*OFFSET(K$2,0,0,COUNTA('Mii List'!A$2:A$200),1))>0)*(ROW(OFFSET($A$2,0,0,COUNTA('Mii List'!A$2:A$200),1))<>ROW())*IF(OFFSET(L$2,0,0,COUNTA('Mii List'!A$2:A$200),1)>0,1/OFFSET(L$2,0,0,COUNTA('Mii List'!A$2:A$200),1),0)))} -> 0.41771529 | O6: {=IF(A6="","",IF(L6=0,0,SUMPRODUCT(((OFFSET(F$2,0,0,COUNTA('Mii List'!A$2:A$200),1)*I6+OFFSET(G$2,0,0,COUNTA('Mii List'!A$2:A$200),1)*J6+OFFSET(H$2,0,0,COUNTA('Mii List'!A$2:A$200),1)*K6)>0)*((F6*OFFSET(I$2,0,0,COUNTA('Mii List'!A$2:A$200),1)+G6*OFFSET(J$2,0,0,COUNTA('Mii List'!A$2:A$200),1)+H6*OFFSET(K$2,0,0,COUNTA('Mii List'!A$2:A$200),1))>0)*(ROW(OFFSET($A$2,0,0,COUNTA('Mii List'!A$2:A$200),1))<>ROW())*OFFSET(L$2,0,0,COUNTA('Mii List'!A$2:A$200),1))/L6))} -> 34.5 | P6: =IF(A6="","",IF(L6*O6>0,MIN(1,L6/O6),0)) -> 0.4057971
A7: {=IF(ROW()-1>COUNTA('Mii List'!A$2:A$200),"",INDEX('Mii List'!A$2:A$200,ROW()-1))} -> Michael Newman | B7: =IF(A7="","",INDEX('Mii List'!B$2:B$200,MATCH(A7,'Mii List'!A$2:A$200,0))) -> Male | C7: =IF(A7="","",INDEX('Mii List'!C$2:C$200,MATCH(A7,'Mii List'!A$2:A$200,0))) -> ✓ | D7: =IF(A7="","",INDEX('Mii List'!D$2:D$200,MATCH(A7,'Mii List'!A$2:A$200,0))) -> ✓ | E7: =IF(A7="","",INDEX('Mii List'!E$2:E$200,MATCH(A7,'Mii List'!A$2:A$200,0))) -> ✓ | F7: =IF(A7="",0,(C7="✓")*1) -> 1 | G7: =IF(A7="",0,(D7="✓")*1) -> 1 | H7: =IF(A7="",0,(E7="✓")*1) -> 1 | I7: =IF(A7="",0,(B7="Male")*1) -> 1 | J7: =IF(A7="",0,(B7="Female")*1) -> 0 | K7: =IF(A7="",0,(B7="Nonbinary")*1) -> 0 | L7: {=IF(A7="",0,SUMPRODUCT((A$2:A$201<>"")*((F$2:F$201*I7+G$2:G$201*J7+H$2:H$201*K7)>0)*((F7*I$2:I$201+G7*J$2:J$201+H7*K$2:K$201)>0))-IF(F7*I7+G7*J7+H7*K7>0,1,0))} -> 32 | M7: {=IF(A7="","",SUMPRODUCT((A$2:A$201<>"")*(L$2:L$201<L7))+SUMPRODUCT((A$2:A$201<>"")*(L$2:L$201=L7)*(A$2:A$201<A7))+1)} -> 37 | N7: {=IF(A7="","",SUMPRODUCT(((OFFSET(F$2,0,0,COUNTA('Mii List'!A$2:A$200),1)*I7+OFFSET(G$2,0,0,COUNTA('Mii List'!A$2:A$200),1)*J7+OFFSET(H$2,0,0,COUNTA('Mii List'!A$2:A$200),1)*K7)>0)*((F7*OFFSET(I$2,0,0,COUNTA('Mii List'!A$2:A$200),1)+G7*OFFSET(J$2,0,0,COUNTA('Mii List'!A$2:A$200),1)+H7*OFFSET(K$2,0,0,COUNTA('Mii List'!A$2:A$200),1))>0)*(ROW(OFFSET($A$2,0,0,COUNTA('Mii List'!A$2:A$200),1))<>ROW())*IF(OFFSET(L$2,0,0,COUNTA('Mii List'!A$2:A$200),1)>0,1/OFFSET(L$2,0,0,COUNTA('Mii List'!A$2:A$200),1),0)))} -> 1.1546167 | O7: {=IF(A7="","",IF(L7=0,0,SUMPRODUCT(((OFFSET(F$2,0,0,COUNTA('Mii List'!A$2:A$200),1)*I7+OFFSET(G$2,0,0,COUNTA('Mii List'!A$2:A$200),1)*J7+OFFSET(H$2,0,0,COUNTA('Mii List'!A$2:A$200),1)*K7)>0)*((F7*OFFSET(I$2,0,0,COUNTA('Mii List'!A$2:A$200),1)+G7*OFFSET(J$2,0,0,COUNTA('Mii List'!A$2:A$200),1)+H7*OFFSET(K$2,0,0,COUNTA('Mii List'!A$2:A$200),1))>0)*(ROW(OFFSET($A$2,0,0,COUNTA('Mii List'!A$2:A$200),1))<>ROW())*OFFSET(L$2,0,0,COUNTA('Mii List'!A$2:A$200),1))/L7))} -> 30.03125 | P7: =IF(A7="","",IF(L7*O7>0,MIN(1,L7/O7),0)) -> 1
A8: {=IF(ROW()-1>COUNTA('Mii List'!A$2:A$200),"",INDEX('Mii List'!A$2:A$200,ROW()-1))} -> Morty | B8: =IF(A8="","",INDEX('Mii List'!B$2:B$200,MATCH(A8,'Mii List'!A$2:A$200,0))) -> Male | C8: =IF(A8="","",INDEX('Mii List'!C$2:C$200,MATCH(A8,'Mii List'!A$2:A$200,0))) -> ✓ | D8: =IF(A8="","",INDEX('Mii List'!D$2:D$200,MATCH(A8,'Mii List'!A$2:A$200,0))) -> ✗ | E8: =IF(A8="","",INDEX('Mii List'!E$2:E$200,MATCH(A8,'Mii List'!A$2:A$200,0))) -> ✗ | F8: =IF(A8="",0,(C8="✓")*1) -> 1 | G8: =IF(A8="",0,(D8="✓")*1) -> 0 | H8: =IF(A8="",0,(E8="✓")*1) -> 0 | I8: =IF(A8="",0,(B8="Male")*1) -> 1 | J8: =IF(A8="",0,(B8="Female")*1) -> 0 | K8: =IF(A8="",0,(B8="Nonbinary")*1) -> 0 | L8: {=IF(A8="",0,SUMPRODUCT((A$2:A$201<>"")*((F$2:F$201*I8+G$2:G$201*J8+H$2:H$201*K8)>0)*((F8*I$2:I$201+G8*J$2:J$201+H8*K$2:K$201)>0))-IF(F8*I8+G8*J8+H8*K8>0,1,0))} -> 17 | M8: {=IF(A8="","",SUMPRODUCT((A$2:A$201<>"")*(L$2:L$201<L8))+SUMPRODUCT((A$2:A$201<>"")*(L$2:L$201=L8)*(A$2:A$201<A8))+1)} -> 21 | N8: {=IF(A8="","",SUMPRODUCT(((OFFSET(F$2,0,0,COUNTA('Mii List'!A$2:A$200),1)*I8+OFFSET(G$2,0,0,COUNTA('Mii List'!A$2:A$200),1)*J8+OFFSET(H$2,0,0,COUNTA('Mii List'!A$2:A$200),1)*K8)>0)*((F8*OFFSET(I$2,0,0,COUNTA('Mii List'!A$2:A$200),1)+G8*OFFSET(J$2,0,0,COUNTA('Mii List'!A$2:A$200),1)+H8*OFFSET(K$2,0,0,COUNTA('Mii List'!A$2:A$200),1))>0)*(ROW(OFFSET($A$2,0,0,COUNTA('Mii List'!A$2:A$200),1))<>ROW())*IF(OFFSET(L$2,0,0,COUNTA('Mii List'!A$2:A$200),1)>0,1/OFFSET(L$2,0,0,COUNTA('Mii List'!A$2:A$200),1),0)))} -> 0.66584967 | O8: {=IF(A8="","",IF(L8=0,0,SUMPRODUCT(((OFFSET(F$2,0,0,COUNTA('Mii List'!A$2:A$200),1)*I8+OFFSET(G$2,0,0,COUNTA('Mii List'!A$2:A$200),1)*J8+OFFSET(H$2,0,0,COUNTA('Mii List'!A$2:A$200),1)*K8)>0)*((F8*OFFSET(I$2,0,0,COUNTA('Mii List'!A$2:A$200),1)+G8*OFFSET(J$2,0,0,COUNTA('Mii List'!A$2:A$200),1)+H8*OFFSET(K$2,0,0,COUNTA('Mii List'!A$2:A$200),1))>0)*(ROW(OFFSET($A$2,0,0,COUNTA('Mii List'!A$2:A$200),1))<>ROW())*OFFSET(L$2,0,0,COUNTA('Mii List'!A$2:A$200),1))/L8))} -> 27.647059 | P8: =IF(A8="","",IF(L8*O8>0,MIN(1,L8/O8),0)) -> 0.61489362
A9: {=IF(ROW()-1>COUNTA('Mii List'!A$2:A$200),"",INDEX('Mii List'!A$2:A$200,ROW()-1))} -> Ben | B9: =IF(A9="","",INDEX('Mii List'!B$2:B$200,MATCH(A9,'Mii List'!A$2:A$200,0))) -> Male | C9: =IF(A9="","",INDEX('Mii List'!C$2:C$200,MATCH(A9,'Mii List'!A$2:A$200,0))) -> ✗ | D9: =IF(A9="","",INDEX('Mii List'!D$2:D$200,MATCH(A9,'Mii List'!A$2:A$200,0))) -> ✓ | E9: =IF(A9="","",INDEX('Mii List'!E$2:E$200,MATCH(A9,'Mii List'!A$2:A$200,0))) -> ✗ | F9: =IF(A9="",0,(C9="✓")*1) -> 0 | G9: =IF(A9="",0,(D9="✓")*1) -> 1 | H9: =IF(A9="",0,(E9="✓")*1) -> 0 | I9: =IF(A9="",0,(B9="Male")*1) -> 1 | J9: =IF(A9="",0,(B9="Female")*1) -> 0 | K9: =IF(A9="",0,(B9="Nonbinary")*1) -> 0 | L9: {=IF(A9="",0,SUMPRODUCT((A$2:A$201<>"")*((F$2:F$201*I9+G$2:G$201*J9+H$2:H$201*K9)>0)*((F9*I$2:I$201+G9*J$2:J$201+H9*K$2:K$201)>0))-IF(F9*I9+G9*J9+H9*K9>0,1,0))} -> 14 | M9: {=IF(A9="","",SUMPRODUCT((A$2:A$201<>"")*(L$2:L$201<L9))+SUMPRODUCT((A$2:A$201<>"")*(L$2:L$201=L9)*(A$2:A$201<A9))+1)} -> 5 | N9: {=IF(A9="","",SUMPRODUCT(((OFFSET(F$2,0,0,COUNTA('Mii List'!A$2:A$200),1)*I9+OFFSET(G$2,0,0,COUNTA('Mii List'!A$2:A$200),1)*J9+OFFSET(H$2,0,0,COUNTA('Mii List'!A$2:A$200),1)*K9)>0)*((F9*OFFSET(I$2,0,0,COUNTA('Mii List'!A$2:A$200),1)+G9*OFFSET(J$2,0,0,COUNTA('Mii List'!A$2:A$200),1)+H9*OFFSET(K$2,0,0,COUNTA('Mii List'!A$2:A$200),1))>0)*(ROW(OFFSET($A$2,0,0,COUNTA('Mii List'!A$2:A$200),1))<>ROW())*IF(OFFSET(L$2,0,0,COUNTA('Mii List'!A$2:A$200),1)>0,1/OFFSET(L$2,0,0,COUNTA('Mii List'!A$2:A$200),1),0)))} -> 0.41771529 | O9: {=IF(A9="","",IF(L9=0,0,SUMPRODUCT(((OFFSET(F$2,0,0,COUNTA('Mii List'!A$2:A$200),1)*I9+OFFSET(G$2,0,0,COUNTA('Mii List'!A$2:A$200),1)*J9+OFFSET(H$2,0,0,COUNTA('Mii List'!A$2:A$200),1)*K9)>0)*((F9*OFFSET(I$2,0,0,COUNTA('Mii List'!A$2:A$200),1)+G9*OFFSET(J$2,0,0,COUNTA('Mii List'!A$2:A$200),1)+H9*OFFSET(K$2,0,0,COUNTA('Mii List'!A$2:A$200),1))>0)*(ROW(OFFSET($A$2,0,0,COUNTA('Mii List'!A$2:A$200),1))<>ROW())*OFFSET(L$2,0,0,COUNTA('Mii List'!A$2:A$200),1))/L9))} -> 34.5 | P9: =IF(A9="","",IF(L9*O9>0,MIN(1,L9/O9),0)) -> 0.4057971
A10: {=IF(ROW()-1>COUNTA('Mii List'!A$2:A$200),"",INDEX('Mii List'!A$2:A$200,ROW()-1))} -> Bea | B10: =IF(A10="","",INDEX('Mii List'!B$2:B$200,MATCH(A10,'Mii List'!A$2:A$200,0))) -> Female | C10: =IF(A10="","",INDEX('Mii List'!C$2:C$200,MATCH(A10,'Mii List'!A$2:A$200,0))) -> ✓ | D10: =IF(A10="","",INDEX('Mii List'!D$2:D$200,MATCH(A10,'Mii List'!A$2:A$200,0))) -> ✗ | E10: =IF(A10="","",INDEX('Mii List'!E$2:E$200,MATCH(A10,'Mii List'!A$2:A$200,0))) -> ✗ | F10: =IF(A10="",0,(C10="✓")*1) -> 1 | G10: =IF(A10="",0,(D10="✓")*1) -> 0 | H10: =IF(A10="",0,(E10="✓")*1) -> 0 | I10: =IF(A10="",0,(B10="Male")*1) -> 0 | J10: =IF(A10="",0,(B10="Female")*1) -> 1 | K10: =IF(A10="",0,(B10="Nonbinary")*1) -> 0 | L10: {=IF(A10="",0,SUMPRODUCT((A$2:A$201<>"")*((F$2:F$201*I10+G$2:G$201*J10+H$2:H$201*K10)>0)*((F10*I$2:I$201+G10*J$2:J$201+H10*K$2:K$201)>0))-IF(F10*I10+G10*J10+H10*K10>0,1,0))} -> 26 | M10: {=IF(A10="","",SUMPRODUCT((A$2:A$201<>"")*(L$2:L$201<L10))+SUMPRODUCT((A$2:A$201<>"")*(L$2:L$201=L10)*(A$2:A$201<A10))+1)} -> 25 | N10: {=IF(A10="","",SUMPRODUCT(((OFFSET(F$2,0,0,COUNTA('Mii List'!A$2:A$200),1)*I10+OFFSET(G$2,0,0,COUNTA('Mii List'!A$2:A$200),1)*J10+OFFSET(H$2,0,0,COUNTA('Mii List'!A$2:A$200),1)*K10)>0)*((F10*OFFSET(I$2,0,0,COUNTA('Mii List'!A$2:A$200),1)+G10*OFFSET(J$2,0,0,COUNTA('Mii List'!A$2:A$200),1)+H10*OFFSET(K$2,0,0,COUNTA('Mii List'!A$2:A$200),1))>0)*(ROW(OFFSET($A$2,0,0,COUNTA('Mii List'!A$2:A$200),1))<>ROW())*IF(OFFSET(L$2,0,0,COUNTA('Mii List'!A$2:A$200),1)>0,1/OFFSET(L$2,0,0,COUNTA('Mii List'!A$2:A$200),1),0)))} -> 1.3702381 | O10: {=IF(A10="","",IF(L10=0,0,SUMPRODUCT(((OFFSET(F$2,0,0,COUNTA('Mii List'!A$2:A$200),1)*I10+OFFSET(G$2,0,0,COUNTA('Mii List'!A$2:A$200),1)*J10+OFFSET(H$2,0,0,COUNTA('Mii List'!A$2:A$200),1)*K10)>0)*((F10*OFFSET(I$2,0,0,COUNTA('Mii List'!A$2:A$200),1)+G10*OFFSET(J$2,0,0,COUNTA('Mii List'!A$2:A$200),1)+H10*OFFSET(K$2,0,0,COUNTA('Mii List'!A$2:A$200),1))>0)*(ROW(OFFSET($A$2,0,0,COUNTA('Mii List'!A$2:A$200),1))<>ROW())*OFFSET(L$2,0,0,COUNTA('Mii List'!A$2:A$200),1))/L10))} -> 22.346154 | P10: =IF(A10="","",IF(L10*O10>0,MIN(1,L10/O10),0)) -> 1
A11: {=IF(ROW()-1>COUNTA('Mii List'!A$2:A$200),"",INDEX('Mii List'!A$2:A$200,ROW()-1))} -> Bill Nye | B11: =IF(A11="","",INDEX('Mii List'!B$2:B$200,MATCH(A11,'Mii List'!A$2:A$200,0))) -> Male | C11: =IF(A11="","",INDEX('Mii List'!C$2:C$200,MATCH(A11,'Mii List'!A$2:A$200,0))) -> ✗ | D11: =IF(A11="","",INDEX('Mii List'!D$2:D$200,MATCH(A11,'Mii List'!A$2:A$200,0))) -> ✓ | E11: =IF(A11="","",INDEX('Mii List'!E$2:E$200,MATCH(A11,'Mii List'!A$2:A$200,0))) -> ✗ | F11: =IF(A11="",0,(C11="✓")*1) -> 0 | G11: =IF(A11="",0,(D11="✓")*1) -> 1 | H11: =IF(A11="",0,(E11="✓")*1) -> 0 | I11: =IF(A11="",0,(B11="Male")*1) -> 1 | J11: =IF(A11="",0,(B11="Female")*1) -> 0 | K11: =IF(A11="",0,(B11="Nonbinary")*1) -> 0 | L11: {=IF(A11="",0,SUMPRODUCT((A$2:A$201<>"")*((F$2:F$201*I11+G$2:G$201*J11+H$2:H$201*K11)>0)*((F11*I$2:I$201+G11*J$2:J$201+H11*K$2:K$201)>0))-IF(F11*I11+G11*J11+H11*K11>0,1,0))} -> 14 | M11: {=IF(A11="","",SUMPRODUCT((A$2:A$201<>"")*(L$2:L$201<L11))+SUMPRODUCT((A$2:A$201<>"")*(L$2:L$201=L11)*(A$2:A$201<A11))+1)} -> 7 | N11: {=IF(A11="","",SUMPRODUCT(((OFFSET(F$2,0,0,COUNTA('Mii List'!A$2:A$200),1)*I11+OFFSET(G$2,0,0,COUNTA('Mii List'!A$2:A$200),1)*J11+OFFSET(H$2,0,0,COUNTA('Mii List'!A$2:A$200),1)*K11)>0)*((F11*OFFSET(I$2,0,0,COUNTA('Mii List'!A$2:A$200),1)+G11*OFFSET(J$2,0,0,COUNTA('Mii List'!A$2:A$200),1)+H11*OFFSET(K$2,0,0,COUNTA('Mii List'!A$2:A$200),1))>0)*(ROW(OFFSET($A$2,0,0,COUNTA('Mii List'!A$2:A$200),1))<>ROW())*IF(OFFSET(L$2,0,0,COUNTA('Mii List'!A$2:A$200),1)>0,1/OFFSET(L$2,0,0,COUNTA('Mii List'!A$2:A$200),1),0)))} -> 0.41771529 | O11: {=IF(A11="","",IF(L11=0,0,SUMPRODUCT(((OFFSET(F$2,0,0,COUNTA('Mii List'!A$2:A$200),1)*I11+OFFSET(G$2,0,0,COUNTA('Mii List'!A$2:A$200),1)*J11+OFFSET(H$2,0,0,COUNTA('Mii List'!A$2:A$200),1)*K11)>0)*((F11*OFFSET(I$2,0,0,COUNTA('Mii List'!A$2:A$200),1)+G11*OFFSET(J$2,0,0,COUNTA('Mii List'!A$2:A$200),1)+H11*OFFSET(K$2,0,0,COUNTA('Mii List'!A$2:A$200),1))>0)*(ROW(OFFSET($A$2,0,0,COUNTA('Mii List'!A$2:A$200),1))<>ROW())*OFFSET(L$2,0,0,COUNTA('Mii List'!A$2:A$200),1))/L11))} -> 34.5 | P11: =IF(A11="","",IF(L11*O11>0,MIN(1,L11/O11),0)) -> 0.4057971
A12: {=IF(ROW()-1>COUNTA('Mii List'!A$2:A$200),"",INDEX('Mii List'!A$2:A$200,ROW()-1))} -> Justin Trudeau | B12: =IF(A12="","",INDEX('Mii List'!B$2:B$200,MATCH(A12,'Mii List'!A$2:A$200,0))) -> Male | C12: =IF(A12="","",INDEX('Mii List'!C$2:C$200,MATCH(A12,'Mii List'!A$2:A$200,0))) -> ✗ | D12: =IF(A12="","",INDEX('Mii List'!D$2:D$200,MATCH(A12,'Mii List'!A$2:A$200,0))) -> ✓ | E12: =IF(A12="","",INDEX('Mii List'!E$2:E$200,MATCH(A12,'Mii List'!A$2:A$200,0))) -> ✗ | F12: =IF(A12="",0,(C12="✓")*1) -> 0 | G12: =IF(A12="",0,(D12="✓")*1) -> 1 | H12: =IF(A12="",0,(E12="✓")*1) -> 0 | I12: =IF(A12="",0,(B12="Male")*1) -> 1 | J12: =IF(A12="",0,(B12="Female")*1) -> 0 | K12: =IF(A12="",0,(B12="Nonbinary")*1) -> 0 | L12: {=IF(A12="",0,SUMPRODUCT((A$2:A$201<>"")*((F$2:F$201*I12+G$2:G$201*J12+H$2:H$201*K12)>0)*((F12*I$2:I$201+G12*J$2:J$201+H12*K$2:K$201)>0))-IF(F12*I12+G12*J12+H12*K12>0,1,0))} -> 14 | M12: {=IF(A12="","",SUMPRODUCT((A$2:A$201<>"")*(L$2:L$201<L12))+SUMPRODUCT((A$2:A$201<>"")*(L$2:L$201=L12)*(A$2:A$201<A12))+1)} -> 10 | N12: {=IF(A12="","",SUMPRODUCT(((OFFSET(F$2,0,0,COUNTA('Mii List'!A$2:A$200),1)*I12+OFFSET(G$2,0,0,COUNTA('Mii List'!A$2:A$200),1)*J12+OFFSET(H$2,0,0,COUNTA('Mii List'!A$2:A$200),1)*K12)>0)*((F12*OFFSET(I$2,0,0,COUNTA('Mii List'!A$2:A$200),1)+G12*OFFSET(J$2,0,0,COUNTA('Mii List'!A$2:A$200),1)+H12*OFFSET(K$2,0,0,COUNTA('Mii List'!A$2:A$200),1))>0)*(ROW(OFFSET($A$2,0,0,COUNTA('Mii List'!A$2:A$200),1))<>ROW())*IF(OFFSET(L$2,0,0,COUNTA('Mii List'!A$2:A$200),1)>0,1/OFFSET(L$2,0,0,COUNTA('Mii List'!A$2:A$200),1),0)))} -> 0.41771529 | O12: {=IF(A12="","",IF(L12=0,0,SUMPRODUCT(((OFFSET(F$2,0,0,COUNTA('Mii List'!A$2:A$200),1)*I12+OFFSET(G$2,0,0,COUNTA('Mii List'!A$2:A$200),1)*J12+OFFSET(H$2,0,0,COUNTA('Mii List'!A$2:A$200),1)*K12)>0)*((F12*OFFSET(I$2,0,0,COUNTA('Mii List'!A$2:A$200),1)+G12*OFFSET(J$2,0,0,COUNTA('Mii List'!A$2:A$200),1)+H12*OFFSET(K$2,0,0,COUNTA('Mii List'!A$2:A$200),1))>0)*(ROW(OFFSET($A$2,0,0,COUNTA('Mii List'!A$2:A$200),1))<>ROW())*OFFSET(L$2,0,0,COUNTA('Mii List'!A$2:A$200),1))/L12))} -> 34.5 | P12: =IF(A12="","",IF(L12*O12>0,MIN(1,L12/O12),0)) -> 0.4057971
A13: {=IF(ROW()-1>COUNTA('Mii List'!A$2:A$200),"",INDEX('Mii List'!A$2:A$200,ROW()-1))} -> Katy Perry | B13: =IF(A13="","",INDEX('Mii List'!B$2:B$200,MATCH(A13,'Mii List'!A$2:A$200,0))) -> Female | C13: =IF(A13="","",INDEX('Mii List'!C$2:C$200,MATCH(A13,'Mii List'!A$2:A$200,0))) -> ✓ | D13: =IF(A13="","",INDEX('Mii List'!D$2:D$200,MATCH(A13,'Mii List'!A$2:A$200,0))) -> ✗ | E13: =IF(A13="","",INDEX('Mii List'!E$2:E$200,MATCH(A13,'Mii List'!A$2:A$200,0))) -> ✗ | F13: =IF(A13="",0,(C13="✓")*1) -> 1 | G13: =IF(A13="",0,(D13="✓")*1) -> 0 | H13: =IF(A13="",0,(E13="✓")*1) -> 0 | I13: =IF(A13="",0,(B13="Male")*1) -> 0 | J13: =IF(A13="",0,(B13="Female")*1) -> 1 | K13: =IF(A13="",0,(B13="Nonbinary")*1) -> 0 | L13: {=IF(A13="",0,SUMPRODUCT((A$2:A$201<>"")*((F$2:F$201*I13+G$2:G$201*J13+H$2:H$201*K13)>0)*((F13*I$2:I$201+G13*J$2:J$201+H13*K$2:K$201)>0))-IF(F13*I13+G13*J13+H13*K13>0,1,0))} -> 26 | M13: {=IF(A13="","",SUMPRODUCT((A$2:A$201<>"")*(L$2:L$201<L13))+SUMPRODUCT((A$2:A$201<>"")*(L$2:L$201=L13)*(A$2:A$201<A13))+1)} -> 28 | N13: {=IF(A13="","",SUMPRODUCT(((OFFSET(F$2,0,0,COUNTA('Mii List'!A$2:A$200),1)*I13+OFFSET(G$2,0,0,COUNTA('Mii List'!A$2:A$200),1)*J13+OFFSET(H$2,0,0,COUNTA('Mii List'!A$2:A$200),1)*K13)>0)*((F13*OFFSET(I$2,0,0,COUNTA('Mii List'!A$2:A$200),1)+G13*OFFSET(J$2,0,0,COUNTA('Mii List'!A$2:A$200),1)+H13*OFFSET(K$2,0,0,COUNTA('Mii List'!A$2:A$200),1))>0)*(ROW(OFFSET($A$2,0,0,COUNTA('Mii List'!A$2:A$200),1))<>ROW())*IF(OFFSET(L$2,0,0,COUNTA('Mii List'!A$2:A$200),1)>0,1/OFFSET(L$2,0,0,COUNTA('Mii List'!A$2:A$200),1),0)))} -> 1.3702381 | O13: {=IF(A13="","",IF(L13=0,0,SUMPRODUCT(((OFFSET(F$2,0,0,COUNTA('Mii List'!A$2:A$200),1)*I13+OFFSET(G$2,0,0,COUNTA('Mii List'!A$2:A$200),1)*J13+OFFSET(H$2,0,0,COUNTA('Mii List'!A$2:A$200),1)*K13)>0)*((F13*OFFSET(I$2,0,0,COUNTA('Mii List'!A$2:A$200),1)+G13*OFFSET(J$2,0,0,COUNTA('Mii List'!A$2:A$200),1)+H13*OFFSET(K$2,0,0,COUNTA('Mii List'!A$2:A$200),1))>0)*(ROW(OFFSET($A$2,0,0,COUNTA('Mii List'!A$2:A$200),1))<>ROW())*OFFSET(L$2,0,0,COUNTA('Mii List'!A$2:A$200),1))/L13))} -> 22.346154 | P13: =IF(A13="","",IF(L13*O13>0,MIN(1,L13/O13),0)) -> 1
... A201: {=IF(ROW()-1>COUNTA('Mii List'!A$2:A$200),"",INDEX('Mii List'!A$2:A$200,ROW()-1))} | B201: =IF(A201="","",INDEX('Mii List'!B$2:B$200,MATCH(A201,'Mii List'!A$2:A$200,0))) | C201: =IF(A201="","",INDEX('Mii List'!C$2:C$200,MATCH(A201,'Mii List'!A$2:A$200,0))) | D201: =IF(A201="","",INDEX('Mii List'!D$2:D$200,MATCH(A201,'Mii List'!A$2:A$200,0))) | E201: =IF(A201="","",INDEX('Mii List'!E$2:E$200,MATCH(A201,'Mii List'!A$2:A$200,0))) | F201: =IF(A201="",0,(C201="✓")*1) -> 0 | G201: =IF(A201="",0,(D201="✓")*1) -> 0 | H201: =IF(A201="",0,(E201="✓")*1) -> 0 | I201: =IF(A201="",0,(B201="Male")*1) -> 0 | J201: =IF(A201="",0,(B201="Female")*1) -> 0 | K201: =IF(A201="",0,(B201="Nonbinary")*1) -> 0 | L201: {=IF(A201="",0,SUMPRODUCT((A$2:A$201<>"")*((F$2:F$201*I201+G$2:G$201*J201+H$2:H$201*K201)>0)*((F201*I$2:I$201+G201*J$2:J$201+H201*K$2:K$201)>0))-IF(F201*I201+G201*J201+H201*K201>0,1,0))} -> 0 | M201: {=IF(A201="","",SUMPRODUCT((A$2:A$201<>"")*(L$2:L$201<L201))+SUMPRODUCT((A$2:A$201<>"")*(L$2:L$201=L201)*(A$2:A$201<A201))+1)} | N201: {=IF(A201="","",SUMPRODUCT(((OFFSET(F$2,0,0,COUNTA('Mii List'!A$2:A$200),1)*I201+OFFSET(G$2,0,0,COUNTA('Mii List'!A$2:A$200),1)*J201+OFFSET(H$2,0,0,COUNTA('Mii List'!A$2:A$200),1)*K201)>0)*((F201*OFFSET(I$2,0,0,COUNTA('Mii List'!A$2:A$200),1)+G201*OFFSET(J$2,0,0,COUNTA('Mii List'!A$2:A$200),1)+H201*OFFSET(K$2,0,0,COUNTA('Mii List'!A$2:A$200),1))>0)*(ROW(OFFSET($A$2,0,0,COUNTA('Mii List'!A$2:A$200),1))<>ROW())*IF(OFFSET(L$2,0,0,COUNTA('Mii List'!A$2:A$200),1)>0,1/OFFSET(L$2,0,0,COUNTA('Mii List'!A$2:A$200),1),0)))} | O201: {=IF(A201="","",IF(L201=0,0,SUMPRODUCT(((OFFSET(F$2,0,0,COUNTA('Mii List'!A$2:A$200),1)*I201+OFFSET(G$2,0,0,COUNTA('Mii List'!A$2:A$200),1)*J201+OFFSET(H$2,0,0,COUNTA('Mii List'!A$2:A$200),1)*K201)>0)*((F201*OFFSET(I$2,0,0,COUNTA('Mii List'!A$2:A$200),1)+G201*OFFSET(J$2,0,0,COUNTA('Mii List'!A$2:A$200),1)+H201*OFFSET(K$2,0,0,COUNTA('Mii List'!A$2:A$200),1))>0)*(ROW(OFFSET($A$2,0,0,COUNTA('Mii List'!A$2:A$200),1))<>ROW())*OFFSET(L$2,0,0,COUNTA('Mii List'!A$2:A$200),1))/L201))} | P201: =IF(A201="","",IF(L201*O201>0,MIN(1,L201/O201),0))

Sheet LICENSE
A1: Tomodachi Life and Mii are trademarks of Nintendo. This project is not affiliated with or endorsed by Nintendo.
A3: GNU GENERAL PUBLIC LICENSE
A4: Version 2, June 1991
A6: Copyright (C) 1989, 1991 Free Software Foundation, Inc.,
A7: <https://fsf.org/>
A8: Everyone is permitted to copy and distribute verbatim copies
A9: of this license document, but changing it is not allowed.
A11: Preamble
A13: The licenses for most software are designed to take away your
A14: freedom to share and change it. By contrast, the GNU General Public
A15: License is intended to guarantee your freedom to share and change free
A16: software--to make sure the software is free for all its users. This
... A340: Public License instead of this License.
